[
  {
    "doc_id": "pnpk-fraktur-kraniomaksilofasial-2021",
    "page": 5,
    "section_slug": "latar-belakang",
    "section_path": "bab_i/latar-belakang",
    "text": "A. Latar Belakang\nTrauma pada daerah oral dan maksilofasial mendapat perhatian\npenting di dalam dunia kedokteran dan kedokteran gigi karena\nkompleksnya struktur anatomi di daerah mulut, rahang, hidung, dan\nwajah. Pada daerah maksilofasial inilah terjadi fungsi respirasi dan\nmastikasi sehingga kerusakan yang ditimbulkan akibat trauma pada\ndaerah ini seringkali menyebabkan gangguan fungsi maupun estetika\ndaerah disebut di atas.\nTrauma pada daerah fraktur kraniomaksilofasial dapat menyebabkan\nterputusnya kontinuitas tulang daerah tersebut, yang dikenal dengan istilah\nfraktur. Secara anatomi, fraktur pada daerah maksilofasial dapat\ndiklasifikasikan menjadi fraktur dentoalveolar, fraktur mandibula, fraktur\nmaksila, fraktur fasial, fraktur tulang orbita, fraktur nasoorbitoethmoid\ndan fraktur yang merupakan kombinasi dari fraktur tersebut di atas.\nUlasan sistematika yang dipublikasikan pada tahun 2013 menunjukkan\nbahwa fraktur pada daerah mandibula terjadi pada 59.2% kasus trauma\nmaksilofasial.\nTrauma merupakan permasalahan global serta tetap menjadi\npenyebab utama kematian dan disabilitas baik di negara maju maupun\nnegara berkembang. Kecelakaan, jatuh dari ketinggian, dan terluka karena\nbenda tajam/tumpul/mesin merupakan beberapa penyebab cedera yang\njdih.kemkes.go.id\n- 6 -\ntidak disengaja. Etiologi fraktur kraniomaksilofasial, dari data yang\ndikumpulkan dari berbagai negara disebabkan paling banyak oleh\nkekerasan, kecelakaan lalu lintas dan akibat olahraga. Data detail dapat\ndiamati pada Tabel 1.\nDi Indonesia, data etiologi fraktur kraniomaksilofasial, ditemukan\nbahwa kecelakaan lalu lintas masih menjadi penyebab utama (59%), diikuti\ndengan terjatuh (42.1%), dan kekerasan (3.9%). Kejadian trauma lebih\nbanyak terjadi pada pria (59%) dibandingkan pada wanita (41%).\nPenelitian yang dilakukan pada Riskesdas 2018, tercatat bahwa\ncedera di bagian kepala seperti mata, hidung, telinga, mulut, wajah, dan\nleher memiliki insidensi sebesar 11,9% (N= 92.976) di Indonesia.\nKebanyakan pasien yang mengalami trauma dan dibawa ke rumah sakit,\nmengalami cedera wajah, sehingga membutuhkan penanganan dokter\nspesialis terkait yang sesuai dengan kompetensinya. Fraktur\nkraniomaksilofasial meliputi fraktur tunggal sampai fraktur multipel.\nPenting bagi seorang dokter pada lini terdepan di Instalasi Gawat Darurat\n(IGD) untuk mengerti evaluasi awal dari pasien fraktur kraniomaksilofasial,\nmemastikan rencana perawatan telah tersusun dengan baik serta\nmendiagnosis apabila terdapat cedera lain yang lebih serius.\nAustralia New Zealand Jepang Norwegia India\nKekerasan 52 32 15.5 49 25\nKecelakaan 19 30 38.5 14 40\nLalu Lintas\nOlahraga 16 20 16.5 8 4\nJatuh 10 9 28.5 15 24\nIndustri 1.5 - 0.3 9 1.3\nLain2x 1.5 9 0.7 4 1.2\nliteratur 1 2 3 4 5\nTabel 1. Etiologi fraktur kraniomaksilofasial pada berbagai negara\nPada Global status report on road safety (WHO, 2018) disebutkan\nbahwa, setiap tahun di seluruh dunia, ditemukan lebih dari 1,35 juta\nkorban meninggal akibat kecelakaan lalu lintas dan 50 juta orang\nmengalami luka berat. Data kepolisian di Indonesia pada tahun 2019,\ntercatat rata-rata 3 orang meninggal setiap jam akibat kecelakaan lalu\nlintas.\njdih.kemkes.go.id\n- 7 -\nPasien dengan fraktur kraniomaksilofasial memerlukan tata laksana\nyang komprehensif, mulai dari tata laksana kegawatdaruratan, operatif,\nnutrisi, hingga rehabilitasi medik. Intervensi rehabilitasi medik berperan\npenting dalam mengatasi gangguan fungsi pada fraktur\nkraniomaksilofasial bahkan pasca operasi. Penanganan rehabilitasi medik\nperlu segera ditindaklanjuti karena berdampak luas bagi penderita\nsebelum menjadi kecacatan yang menetap. Tata laksana rehabilitasi medik\nmeliputi aspek fisik dan psikis. Masalah psikis seperti depresi, ansietas,\nfrustasi bukan saja sangat mempengaruhi capaian program rehabilitasi\ntetapi juga dapat mengakibatkan gangguan jangka panjang terhadap\nperilaku makan dan nutrisi. Tertundanya penanganan rehabilitasi dapat\nmenyebabkan gangguan adaptasi yang berujung pada penurunan kualitas\nhidup penderita.\nIndent masuk maksilofasial dapat menimbulkan gangguan fungsi\nmengunyah, menelan, bernapas, berbicara, dan aspek estetika pada wajah.\nBila terjadi cedera pada kepala/bagian kranium, maka dapat menyebabkan\ngejala sisa berupa penurunan kognisi. Hal ini dapat diperparah oleh\nkomplikasi pasca rekonstruksi seperti kerusakan saraf, infeksi, maloklusi,\nhematoma, malunion, granuloma, dan lain-lain. Konsekuensi dari cedera\nini memerlukan penanganan rehabilitasi komprehensif jangka panjang\noleh tim Rehabilitasi Medik.",
    "year": 2021,
    "source_type": "pnpk",
    "score": 0.0,
    "retrieval_method": "hybrid",
    "source_url": null
  },
  {
    "doc_id": "pnpk-fraktur-kraniomaksilofasial-2021",
    "page": 7,
    "section_slug": "permasalahan",
    "section_path": "bab_i/permasalahan",
    "text": "B. Permasalahan\nPrevalensi cedera nasional adalah 8,2% dan kecelakaan lalu lintas,\nkecelakaan kerja, dan jatuh dari ketinggian masih menjadi penyebab\nutama fraktur kraniomaksilofasial di Indonesia. Kasus fraktur\nkraniomaksilofasial seringkali merupakan kasus kedaruratan yang perlu\nditangani dengan cepat.\nKeterlambatan diagnosis fraktur kraniomaksilofasial dapat\nmengancam jiwa serta menyebabkan gangguan anatomi dan fungsi yang\nberat. Kasus fraktur kraniomaksilofasial memiliki risiko komplikasi seperti\nkecacatan menetap berupa gangguan fungsi dan estetika. Beberapa\nkecacatan fungsi seperti gangguan kognisi, obstruksi jalan nafas,\ngangguan penglihatan, gangguan penghidu, gangguan mengunyah,\ngangguan bicara, gangguan keseimbangan, gangguan sensori wajah, serta\ninfeksi kronis.\njdih.kemkes.go.id\n- 8 -\nPenanganan kasus fraktur kraniomaksilofasial sangat kompleks\nmemiliki variasi tinggi dalam teknik diagnosis, terapi medikamentosa,\nteknik operatif, perawatan, dan rehabilitasi sehingga memerlukan\nkerjasama interdisipliner yang baik untuk mendapatkan hasil yang\noptimal. Belum ada panduan nasional yang komprehensif dalam tata\nlaksana fraktur kraniomaksilofasial.",
    "year": 2021,
    "source_type": "pnpk",
    "score": 0.0,
    "retrieval_method": "hybrid",
    "source_url": null
  },
  {
    "doc_id": "pnpk-fraktur-kraniomaksilofasial-2021",
    "page": 8,
    "section_slug": "tujuan",
    "section_path": "bab_i/tujuan",
    "text": "C. Tujuan\n1. Tujuan Umum\nTerwujudnya panduan nasional tata laksana komprehensif fraktur\nkraniomaksilofasial.\n2. Tujuan Khusus\na. Membuat rekomendasi berdasarkan bukti ilmiah (scientific\nevidence) untuk membantu para praktisi dalam melakukan\ndiagnosis, evaluasi dan tata laksana fraktur kraniomaksilofasial.\nb. Memberi rekomendasi bagi rumah sakit/penentu kebijakan\nuntuk penyusunan protokol setempat atau Panduan Praktik\nKlinis (PPK), dengan melakukan adaptasi terhadap Pedoman\nNasional Pelayanan Kedokteran (PNPK) ini.\nc. Adanya panduan yang bersifat nasional dengan mengutamakan\nkepentingan pasien sehingga didapatkan hasil yang optimal\nsecara fungsional dan estetik pada pasien.",
    "year": 2021,
    "source_type": "pnpk",
    "score": 0.0,
    "retrieval_method": "hybrid",
    "source_url": null
  },
  {
    "doc_id": "pnpk-fraktur-kraniomaksilofasial-2021",
    "page": 8,
    "section_slug": "sasaran",
    "section_path": "bab_i/sasaran",
    "text": "D. Sasaran\n1. Semua tenaga medis, dokter umum dan dokter gigi yang terlibat dalam\npenanganan kasus fraktur kraniomaksilofasial.\n2. Dokter spesialis yang mempunyai kompetensi dalam kewenangan\nklinis melakukan tata laksana fraktur kraniomaksilofasial antara lain\ndokter spesialis Bedah Mulut dan Maksilofasial, THT-KL, Mata, Bedah\nPlastik, Bedah Umum, Bedah Syaraf, Bedah Kepala Leher, Anestesi,\nNeurologi, Kedokteran Fisik dan Rehabilitasi Medik, Gizi Klinik,\nOrthodonti, Prosthodonti, dan Radiologi.\n3. Pembuat kebijakan di lingkungan rumah sakit, institusi pendidikan,\nserta kelompok profesi terkait.\njdih.kemkes.go.id\n- 9 -",
    "year": 2021,
    "source_type": "pnpk",
    "score": 0.0,
    "retrieval_method": "hybrid",
    "source_url": null
  },
  {
    "doc_id": "pnpk-fraktur-kraniomaksilofasial-2021",
    "page": 9,
    "section_slug": "penelusuran-kepustakaan",
    "section_path": "bab_ii/penelusuran-kepustakaan",
    "text": "A. Penelusuran Kepustakaan\nPenyusunan PNPK dilakukan dengan pendekatan berdasarkan bukti\nilmiah, di mana semua studi baik primer dan sekunder dikumpulkan,\ndiseleksi, ditelaah kritis, dan dilaporkan secara sistematik, objektif, dan\ntransparan. Penelusuran kepustakaan dilakukan secara elektronik dan\nsecara manual. Penelusuran secara elektronik diawali dengan mencari\npedoman Internasional yang telah ada sebelumnya, melalui DynaMed dan\nNational Institute for Health and Care Excellence (NICE). Pencarian studi\nprimer/individual dan sekunder lainnya (systematic review dan/atau meta-\nanalisis), dilakukan melalui situs PubMed, layanan informasi Elton Bryson\nStephen, Co. (EBSCO), dan The Cochrane Central Register of Controlled\nTrials (CENTRAL). Kami menggunakan kata kunci dan Medical Subject\nHeading (MeSH) term yang relevan dengan trauma atau fraktur\nmaksilofasial.\nPenelusuran secara manual dilakukan pada",
    "year": 2021,
    "source_type": "pnpk",
    "score": 0.0,
    "retrieval_method": "hybrid",
    "source_url": null
  }
]