[
  {
    "doc_id": "pnpk-kusta-2019",
    "page": 4,
    "section_slug": "latar-belakang",
    "section_path": "bab_1/latar-belakang",
    "text": "A. Latar Belakang\nPenyakit kusta merupakan salah satu penyakit menular yang\nmenimbulkan masalah yang sangat kompleks. Masalah yang dimaksud\nbukan hanya dari segi medis tetapi meluas hingga masalah sosial, ekonomi,\nbudaya, keamanan dan ketahanan nasional.\nPenyakit kusta pada umumnya terdapat di negara-negara yang sedang\nberkembang sebagai akibat keterbatasan kemampuan negara tersebut\nuntuk memberikan pelayanan yang memadai dalam bidang kesehatan,\npendidikan, dan kesejahteraan sosial serta ekonomi pada masyarakat.\nTahun 2016, WHO mengeluarkan “Global leprosy strategy 2016–2020:\nMempercepat dunia bebas kusta yang dijadikan sebagai momentum\nprogram kusta secara global dan lokal. Target dalam strategi global adalah:\n1) Tidak ada cacat tingkat 2 pada anak dengan diagnosis kusta; 2)\nMenurunkan kasus baru dengan cacat tingkat 2 di bawah 1/1000.000\npenduduk; dan 3) Tidak ada negara yang melakukan diskriminasi berbasis\npada kusta. Target-target ini sangat baik dan mengesankan, namun ini\nsangat ambisius dan sulit dicapai dalam 5 tahun kedepan. Tujuan lainnya\ntermasuk promosi penemuan kasus secara dini melalui kampanye aktif\ncase finding didaerah endemis tinggi, memperkuat surveilans resistensi\nobat termasuk jejaring laboratorium dan langkah-langkah menghentikan\ndiskriminasi dan promosi inklusi kusta di masyarakat luas. Global leprosy\nstrategy juga masuk dalam “Roadmap for Neglected Tropical Diseases”\nuntuk promosi integrasi dengan pelayanan dasar dan kasus rujukan.\n- 5 -\nPada Juli 2013, Deklarasi Bangkok yang ditandatangani oleh Menteri\nKesehatan Negara Endemis Tinggi Kusta termasuk Indonesia, WHO serta\nstakeholder terkait, menyepakati dilanjutkannya upaya-upaya inovatif demi\nmendorong pencapaian status eliminasi pada tingkat sub-nasional tahun\n2019. Di samping itu ditetapan pula target angka cacat tingkat 2 di bawah\n1/1.000.000 penduduk pada tahun 2020. Indonesia telah mencapai status\neliminasi nasional pada tahun 2000, tetapi situasi epidemiologi kusta di\nIndonesia hingga saat ini cenderung statis dengan angka pencapaian kasus\nbaru berkisar 17.000-20.000 kasus tiap tahunnya.\nAngka kasus kusta baru di Indonesia pada tahun 2016 dilaporkan\n16.826 kasus dengan angka prevalensi 0,71 per 10.000 penduduk dan\nangka penemuan kasus baru sebesar 6,5 per 100.000 penduduk. Di antara\nkasus baru tersebut, 83% merupakan kasus MB (Multi Basiler), 9% kasus\ncacat tingkat 2 dan 11% kasus anak. Tingginya proporsi kasus MB, cacat\ntingkat 2 dan kasus anak di Indonesia, menunjukkan masih\nberlangsungnya penularan dan masih tingginya angka keterlambatan\ndalam penemuan kasus baru. Saat ini masih terdapat 11 provinsi di\nIndonesia dengan angka prevalensi lebih dari 1 kasus per 10.000\npenduduk. Berdasarkan data tahun 2016, masih ada 139 kabupaten/kota\ndengan prevalensi masih di atas 1/10.000 penduduk. Upaya untuk\nmencapai eliminasi kusta di tingkat kabupaten/kota ini akan mendorong\ntercapainya eliminasi pada tingkat provinsi.\nUpaya pengendalian penyakit kusta di dunia menetapkan tahun 2000\nsebagai tonggak pencapaian eliminasi. Indonesia berhasil mencapai target\nini pada tahun yang sama, akan tetapi perkembangan 10 tahun terakhir\nmemperlihatkan kecenderungan statis dalam penemuan kasus baru.\nSebagai upaya global, WHO yang didukung ILEP (International Federation\nof Anti Leprosy Associations) mengeluarkan Enhanced Global Strategy for\nFurther Reducing the Disease Burden due to Leprosy (2011-2015).\nBerpedoman pada panduan WHO ini dan menyelaraskan dengan Rencana\nStrategi Kementerian Kesehatan tahun 2015-2019, maka disusunlah\nkebijakan nasional pengendalian kusta di Indonesia.\nSecara epidemiologi penyakit kusta di dunia dan khususnya di\nIndonesia, dibagi 2 menurut distribusinya, sebagai berikut:\n- 6 -\n1. Distribusi penyakit kusta menurut geografi\nWHO melaporkan data yang terkumpul dari 143 negara pada tahun\n2016 yaitu kasus baru yang terdeteksi sebanyak 214.783 dan yang\nterdaftar sebanyak 171.948 (angka prevalensi 0,23 per 10.000\npenduduk). Dari jumlah kasus baru yang ditemukan paling banyak\nterdapat di wilayah Asia Tenggara (115.180) diikuti wilayah Amerika\n(26.365), Afrika (21.465), dan sisanya berada di wilayah lain di dunia.\nDistribusi kasus kusta di Indonesia menyebar hampir di seluruh\npropinsi dengan daerah kantong di kabupaten atau kecamatan\ntertentu. Beberapa propinsi di wilayah timur Indonesia masih\nmerupakan propinsi endemis tinggi.\nDistribusi angka penemuan kasus baru kusta di Indonesia terlihat\npada gambar 1\nGambar 1. Peta Distribusi Kasus Kusta Tingkat Provinsi di Indonesia\ntahun 2016.\n2. Distribusi menurut faktor manusia\nFaktor-faktor yang memengaruhi adalah etnik atau suku, sosial\nekonomi, usia, dan jenis kelamin. Di Myanmar kejadian kusta\nlepromatosa lebih sering pada etnik Burma dibandingkan dengan etnik\nIndia. Situasi di Malaysia juga menunjukkan hal yang sama, kejadian\nkusta lepromatosa lebih banyak pada etnik Cina dibandingkan etnik\nMelayu atau India.\nDistribusi penyakit kusta menurut umur, umumnya dibuat\nberdasarkan prevalensi dan hanya sedikit yang berdasarkan insiden.\n- 7 -\nHal ini disebabkan kesulitan mengetahui saat awal timbulnya\npenyakit. Dengan kata lain, kejadian penyakit lebih mudah dikaitkan\ndengan usia saat ditemukan, ketimbang menentukan awitan penyakit.\nKusta dapat menginfeksi setiap individu berbagai usia, dengan rentang\n3 minggu sampai lebih dari 70 tahun. Namun yang terbanyak adalah\npada usia muda dan produktif, terutama terlihat pada usia 20 hingga\n30 tahun. Pada daerah endemis, infeksi terjadi terutama pada usia\nanak, sebaliknya di daerah endemis rendah lebih banyak pada usia\ndewasa, bahkan di usia lanjut. Proporsi kasus anak di antara kasus\nbaru didapatkan sebanyak 11,43%. Ditemukannya kasus kusta pada\nanak menunjukkan adanya kasus kusta usia dewasa yang belum\ndiobati. Mengacu pada Indian Association of Leprologist (IAL)\ndidapatkan bahwa di berbagai negara di dunia termasuk Indonesia,\nkasus kusta lebih banyak didapatkan pada laki-laki dibandingkan\ndengan perempuan dengan rasio 2:1. Rendahnya kejadian kusta pada\nperempuan kemungkinan karena faktor lingkungan dan sosial budaya.",
    "year": 2019,
    "source_type": "pnpk",
    "score": 0.0,
    "retrieval_method": "hybrid",
    "source_url": "https://kemkes.go.id/app_asset/file_content_download/1701156043656594cb42cf52.71103349.pdf"
  },
  {
    "doc_id": "pnpk-kusta-2019",
    "page": 7,
    "section_slug": "permasalahan",
    "section_path": "bab_1/permasalahan",
    "text": "B. Permasalahan\nKasus kusta baru di Indonesia masih banyak ditemukan, dengan\njumlah bervariasi terutama di wilayah Timur. Hingga tahun 2016, angka\nkecacatan tingkat II didapatkan 5,27/1.000.000 penduduk, dan angka\nkecacatan tingkat II pada anak 0,24 /1.000.000 penduduk. Tingginya\nangka ini antara lain disebabkan oleh: adanya stigma sosial terhadap kusta\nyang cukup tinggi di masyarakat dan tenaga kesehatan menghambat\npenemuan kasus dan tatalaksana kusta, masyarakat belum mengetahui\ngejala awal penyakit kusta, sebagian besar pemegang program\npengendalian kusta bukan dokter, tatalaksana kusta secara komprehensif\n(termasuk pencegahan kecacatan) belum optimal, secara klinis penyakit\nkusta banyak menyerupai penyakit kulit lainnya sehingga diperlukan\npemeriksaan penunjang. Sedangkan fasilitas pemeriksaan penunjang\nuntuk penegakkan diagnosis belum tersedia di semua fasilitas pelayanan\nkesehatan perjalanan penyakit kusta yang sangat panjang sehingga reaksi\nyang timbul setelah pengobatan tidak terpantau, belum adanya\nkeseragaman dalam penatalaksanaan kusta.\n- 8 -",
    "year": 2019,
    "source_type": "pnpk",
    "score": 0.0,
    "retrieval_method": "hybrid",
    "source_url": "https://kemkes.go.id/app_asset/file_content_download/1701156043656594cb42cf52.71103349.pdf"
  },
  {
    "doc_id": "pnpk-kusta-2019",
    "page": 8,
    "section_slug": "tujuan",
    "section_path": "bab_1/tujuan",
    "text": "C. Tujuan\n1. Tujuan umum:\nMembuat pedoman berdasarkan bukti ilmiah untuk para praktisi yang\nmenangani kusta.\n2. Tujuan khusus:\na. Memberi rekomendasi bagi rumah sakit/pembuat keputusan\nklinis untuk menyusun protokol setempat atau Panduan Praktik\nKlinis (PPK) yang mengacu pada Pedoman Nasional Pelayanan\nKedokteran (PNPK) Tata Laksana Kusta.\nb. Meningkatkan angka notifikasi pasien kusta\nc. Mencegah resistensi obat\nd. Menjadi dasar bagi kolegium dokter untuk membuat kurikulum\npendidikan\ne. Menurunkan morbiditas dan disabilitas/kecacatan akibat kusta.",
    "year": 2019,
    "source_type": "pnpk",
    "score": 0.0,
    "retrieval_method": "hybrid",
    "source_url": "https://kemkes.go.id/app_asset/file_content_download/1701156043656594cb42cf52.71103349.pdf"
  },
  {
    "doc_id": "pnpk-kusta-2019",
    "page": 8,
    "section_slug": "sasaran",
    "section_path": "bab_1/sasaran",
    "text": "D. Sasaran\nSasaran Pedoman Nasional Pelayanan Kedokteran Tata Laksana\nKusta, yaitu:\n1. Dokter dan dokter spesialis yang terlibat dalam penanganan kusta\n2. Pembuat keputusan klinis di fasilitas pelayanan kesehatan, institusi\npendidikan dan kelompok profesi terkait.\n- 9 -",
    "year": 2019,
    "source_type": "pnpk",
    "score": 0.0,
    "retrieval_method": "hybrid",
    "source_url": "https://kemkes.go.id/app_asset/file_content_download/1701156043656594cb42cf52.71103349.pdf"
  },
  {
    "doc_id": "pnpk-kusta-2019",
    "page": 9,
    "section_slug": "penelusuran-pustaka",
    "section_path": "bab_2/penelusuran-pustaka",
    "text": "A. Penelusuran Pustaka\nPenelusuran kepustakaan dilakukan secara manual dan elektronik,\nmelalui PUBMED, EBSCO, The Cochrane Laboratory, Textbook Physical\nMedicine and Rehabilitation, Textbook of Leprosy, dengan kata kunci yang\ndigunakan yaitu kusta, reaksi kusta, disabilitas kusta, komplikasi.",
    "year": 2019,
    "source_type": "pnpk",
    "score": 0.0,
    "retrieval_method": "hybrid",
    "source_url": "https://kemkes.go.id/app_asset/file_content_download/1701156043656594cb42cf52.71103349.pdf"
  },
  {
    "doc_id": "pnpk-kusta-2019",
    "page": 9,
    "section_slug": "telaah-kritis",
    "section_path": "bab_2/telaah-kritis",
    "text": "B. Telaah Kritis\nSetiap bukti ilmiah yang diperoleh dilakukan telaah kritis oleh pakar\ndalam bidang Ilmu Kesehatan Kulit dan Kelamin, Ilmu Penyakit Saraf, Ilmu\nKesehatan Mata, Bedah Orthopedi, Ilmu Kesehatan Jiwa serta Kedokteran\nFisik dan Rehabilitasi.",
    "year": 2019,
    "source_type": "pnpk",
    "score": 0.0,
    "retrieval_method": "hybrid",
    "source_url": "https://kemkes.go.id/app_asset/file_content_download/1701156043656594cb42cf52.71103349.pdf"
  },
  {
    "doc_id": "pnpk-kusta-2019",
    "page": 9,
    "section_slug": "peringkat-bukti",
    "section_path": "bab_2/peringkat-bukti",
    "text": "C. Peringkat Bukti\nLevel of evidence (LoE) yang digunakan, yaitu:\n1. Level I : meta analisis, uji klinis besar dengan randomisasi\n2. Level II : uji klinis lebih kecil, tidak dirandomisasi\n3. Level III : penelitian retrospektif, observasional\n4. Level IV : serial kasus, laporan kasus, konsensus, pendapat ahli.",
    "year": 2019,
    "source_type": "pnpk",
    "score": 0.0,
    "retrieval_method": "hybrid",
    "source_url": "https://kemkes.go.id/app_asset/file_content_download/1701156043656594cb42cf52.71103349.pdf"
  },
  {
    "doc_id": "pnpk-kusta-2019",
    "page": 9,
    "section_slug": "derajat-rekomendasi",
    "section_path": "bab_2/derajat-rekomendasi",
    "text": "D. Derajat Rekomendasi\nBerdasarkan LoE di atas, dapat dibuat rekomendasi sebagai berikut:\n1. Rekomendasi A bila berdasar pada bukti level I\n2. Rekomendasi B bila berdasar pada bukti level II\n3. Rekomendasi C bila berdasar pada bukti level III\n4. Rekomendasi D bila berdasar pada bukti level IV\n- 10 -",
    "year": 2019,
    "source_type": "pnpk",
    "score": 0.0,
    "retrieval_method": "hybrid",
    "source_url": "https://kemkes.go.id/app_asset/file_content_download/1701156043656594cb42cf52.71103349.pdf"
  },
  {
    "doc_id": "pnpk-kusta-2019",
    "page": 10,
    "section_slug": "definisi-kusta",
    "section_path": "bab_3/definisi-kusta",
    "text": "A. Definisi Kusta\nKusta adalah penyakit infeksi kronis yang disebabkan oleh kuman\nMycobacterium leprae. Penyakit ini mempunyai afinitas utama pada saraf\ntepi/perifer, kemudian kulit, dan dapat mengenai organ tubuh lain seperti\nmata, mukosa saluran napas atas, otot, tulang dan testis.",
    "year": 2019,
    "source_type": "pnpk",
    "score": 0.0,
    "retrieval_method": "hybrid",
    "source_url": "https://kemkes.go.id/app_asset/file_content_download/1701156043656594cb42cf52.71103349.pdf"
  },
  {
    "doc_id": "pnpk-kusta-2019",
    "page": 10,
    "section_slug": "a-hansen-pada-tahun-1873-di-norwegia-yang-hingga-saat-ini-be",
    "section_path": "bab_3/a-hansen-pada-tahun-1873-di-norwegia-yang-hingga-saat-ini-be",
    "text": "G. A. Hansen pada tahun 1873 di Norwegia, yang hingga saat ini belum\ndapat dibiakkan dalam media artifisial. Namun, pada tahun 1960 Shepard\nberhasil menginokulasikan M. leprae pada kaki mencit, dan berkembang\nbiak di sekitar area tersebut. M. leprae berbentuk batang dengan ukuran 1-\n8 µm x 0,5 µm, bersifat tahan asam dan alkohol serta Gram-positif.\nM. leprae mempunyai patogenitas dan daya invasi yang rendah, sebab\npenderita yang mengandung kuman lebih banyak belum tentu memberikan\ngejala yang lebih berat, bahkan dapat sebaliknya. Basil kusta masuk ke\ntubuh manusia melalui kontak langsung dengan kulit atau mukosa nasal\nyang berasal dari droplet. Basil dari droplet akan bertahan hidup selama 2\nhari dalam lingkungan yang kering, bahkan hingga 10 hari pada lingkungan\nyang lembab dan suhu yang rendah. Setelah infeksi terjadi, gejala klinis\npada saraf perifer atau kulit akan muncul dalam waktu 3 bulan hingga 10\ntahun. Gejala klinis yang timbul bervariasi, bergantung pada sistem\nimunitas selular (SIS) penderita. Bila SIS baik, akan tampak gambaran\nklinis ke arah tuberkuloid, sebaliknya bila SIS rendah memberikan\ngambaran lepromatosa.",
    "year": 2019,
    "source_type": "pnpk",
    "score": 0.0,
    "retrieval_method": "hybrid",
    "source_url": "https://kemkes.go.id/app_asset/file_content_download/1701156043656594cb42cf52.71103349.pdf"
  },
  {
    "doc_id": "pnpk-kusta-2019",
    "page": 10,
    "section_slug": "manifestasi-klinis",
    "section_path": "bab_3/manifestasi-klinis",
    "text": "C. Manifestasi Klinis\n1. Kulit\nKelainan kulit dapat berbentuk makula atau bercak hipopigmetasi\ndengan anestesi, atau makula hipopigmetasi disertai tepi yang\nmenimbul dan sedikit eritematosa, atau berupa infiltrat/plak\neritematosa, atau dapat pula berbentuk papul dan nodul. Kelainan\nkulit ini menyerupai berbagai penyakit kulit lain, sehingga adanya\ngangguan sensibilitas berupa anestesi atau hipoestesi sangat\n- 11 -\nmembantu dalam menegakkan diagnosis kusta. Gambaran klinis kulit\nyang beragam ini dapat digunakan untuk menentukan tipe kusta,\nkarena khas untuk tipe tertentu.\n2. Saraf Perifer\nManifestasi neurologis terbanyak pada kusta ialah adanya kerusakan\nsaraf perifer yang menyertai lesi kulit, terutama pada serabut saraf\nkulit dan trunkus saraf. Gambaran dan distribusi kerusakan saraf\nyang terjadi dipengaruhi oleh jumlah bakteri yang menginfiltrasi saraf,\nserta respons imunologis penderita terhadap saraf yang terinfeksi.\nBerdasarkan hal tersebut, manifestasi klinis kerusakan saraf perifer\ndapat digolongkan menjadi gangguan sensorik, gangguan motorik dan\ngangguan otonom. Ketiga gangguan ini dapat terjadi pada saraf perifer\ndi ekstremitas maupun saraf kranial.\nNeuropati perifer paling sering bermanifestasi sebagai mononeuropati,\npolineuropati atau mononeuropati multipleks. Saraf perifer yang sering\nterkena ialah N.ulnaris, N.radialis, N.medianus, N. poplitea lateralis,\nN. tibialis posterior, N. fasialis, N. trigeminus serta N.auricularis\nmagnus. Gangguan pada saraf perifer tersebut meliputi gangguan\npada cabang saraf sensorik, otonom dan motorik, seperti yang\ndiuraikan berikut ini.\na. N. ulnaris\nGangguan saraf sensorik berupa anestesi pada ujung jari bagian\nanterior kelingking dan jari manis. Sedangkan gangguan saraf\nmotorik menyebabkan clawing jari kelingking dan jari manis,\natrofi hipotenar dan otot interoseus serta kedua otot lumbrikalis\nmedial.\nb. N. medianus\nGangguan saraf sensorik berupa anestesi pada ujung jari bagian\nanterior ibu jari, telunjuk, dan jari tengah. Pada gangguan saraf\nmotorik dapat menyebabkan ibu jari tidak mampu aduksi, serta\nterjadi kontraktur ibu jari. Selain itu, juga terjadi clawing ibu jari,\ntelunjuk, dan jari tengah. Otot tenar dan kedua otot lumbrikalis\nlateral mengalami atrofi.\n- 12 -\nc. N. radialis\nGangguan saraf sensorik berupa anestesi dorsum manus, serta\nujung proksimal jari telunjuk. Pada gangguan saraf motorik,\npergelangan tangan maupun jari-jari tangan tak mampu ekstensi,\nsehingga menyebabkan paresis, disebut sebagai tangan gantung\n(wrist drop).\nd. N. poplitea lateralis\nGangguan saraf sensorik menyebabkan anestesi tungkai bawah\nbagian lateral dan dorsum pedis. Gangguan pada saraf motorik\nmenyebabkan kaki gantung (foot drop) dan kelemahan otot\nperoneus.\ne. N. tibialis posterior\nGangguan saraf sensorik dapat menyebabkab anestesi telapak\nkaki. Sedangkan gangguan motorik berupa claw toes, paralisis\notot intrinsik kaki dan kolaps arkus pedis.\nf. N. fasialis\nGangguan pada cabang temporal dan zigomatik dapat\nmenyebabkan lagoftalmos. Sedangkan gangguan pada cabang\nbukal, mandibular, dan servikal menyebabkan bibir mencong,\nsudut mulut asimetris, dan kegagalan mengatupkan bibir, yang\ndisebut sebagai parese fasialis.\ng. N. trigeminus\nGangguan saraf sensorik menyebabkan anestesi kulit wajah,\nkornea dan konjungtiva.\nh. Kusta saraf murni\nKusta saraf murni atau yang dikenal sebagai pure neural leprosy\n(PNL) merupakan penyakit kusta yang hanya mengenai saraf,\ndengan gambaran klinis hipoestesi atau anestesi tidak berbatas\ntegas, dan tanpa lesi di kulit. Angka kejadian PNL berkisar antara\n4-8% dari kejadian kusta, dan sebagian besar penderitanya\nadalah laki-laki. Keluhan terbanyak ialah gangguan sensorik\npada dermatom yang dipersarafi oleh saraf yang terlibat, dan\ndeformitas atau kelemahan akibat keterlibatan saraf motorik.\nUmumnya PNL mengenai saraf pada ekstremitas atas. Nervus\nulnaris, merupakan yang paling banyak terkena, diikuti dengan\nnervus poplitea lateralis, nervus tibialis posterior, dan nervus\n- 13 -\nsuralis. Pada pemeriksaan fisik, dapat ditemukan adanya\npenebalan dan pembesaran saraf yang dapat didahului nyeri\nneuropatik (sering dikaitkan dengan neuritis) beberapa bulan\nsebelum diagnosis klinis ditegakkan.\nPemeriksaan elektrofisiologi dapat mendeteksi neuropati\nsebelum timbul manifestasi klinis. Indikasi pemeriksaan\nelektrofisiologi pada pasien kusta ialah:\n1) Segera setelah diagnosis kusta untuk mengetahui data dasar\ndan asesmen keterlibatan saraf\n2) Bila muncul gejala dan tanda neuritis atau kerusakan fungsi\nsaraf\nGambar 2. Saraf Perifer yang Banyak Terlibat dan Mengalami Pembesaran\nPada Kusta.\n- 14 -\ni. Indikasi Pemeriksaan Elektrofisiologi pada Kusta\nNeuropati dapat ditemukan bahkan sebelum gejala dan tanda\nkusta muncul atau dikeluhkan oleh pasien. Pemeriksaan\nelektrofisiologi dapat mendeteksi neuropati sebelum timbul\nmanifestasi klinis. Indikasi pemeriksaan elektrofisiologi pada\npasien kusta ialah:\n1) Sebagai pemeriksaan penunjang (bila diperlukan) pada\npasien dengan kecurigaan diagnosis kusta\n2) Segera setelah diagnosis kusta untuk mengetahui data dasar\ndan asesmen keterlibatan saraf\n3) Bila muncul gejala dan tanda neuritis atau kerusakan fungsi\nsaraf\n3. Mata\nKerusakan mata pada penyakit kusta dapat terjadi intraokular\nmaupun ekstraokular. Kerusakan intraokular berupa episkleritis,\nskleritis, iridosiklitis, keratitis, ulkus kornea, serta penurunan\nsensibilitas kornea. Sedangkan kerusakan ekstraokular yang dapat\nterjadi berupa madarosis, lagoftalmus, dakriosistisis, serta mata\nkering. Lebih lanjut, kerusakan mata dapat menyebabkan kebutaan\npadahal penderita kusta sangat bergantung pada penglihatannya\nuntuk mencegah tangan dan kakinya yang kebas mengalami cedera.\nProses kerusakan mata bahkan dapat terus berjalan meskipun\npengobatan lepra sudah tuntas. Risiko kematian pada pasien lepra\nyang buta lebih besar 4.8 kali dibandingkan populasi normal di usia\nyang sama. Dengan demikian continuum of care pada tata laksana\npenyakit kusta penting untuk dilakukan, sehingga usaha pencegahan\nkebutaan serta penanganan kebutaan yang sifatnya masih reversibel\nharus diperhatikan.\n4. Gangguan Psikiatrik\nKusta merupakan penyakit fisik yang sangat erat hubungannya\ndengan dampak psikososial yang dialami oleh pasien. Studi pada\ntahun 1980 menyatakan bahwa prevalensi morbiditas psikiatri pada\npenyakit ini lebih tinggi dibandingkan populasi umum, dengan\n- 15 -\nperbandingan 99:63 diantara 1000 orang. Sejak saat itu para peneliti\nmulai mencari tahu bagaimana hubungan antara dua kondisi ini.\nDeformitas dan stigma yang terkandung pada penyakit inilah yang\nmembuat kehidupan bagi penderita kusta menjadi semakin sulit.\nTidak jarang pasien akan mengalami perceraian, kehilangan\npekerjaan, atau bahkan dijauhi oleh lingkungannya karena ketakutan\nakan gambaran penularan penyakit tersebut.\nMenurut sebuah penelitian di Brazil pada 120 pasien dengan kusta,\nditemukan bahwa sebanyak 71,66% pasien memiliki setidaknya satu\ndiagnosis psikiatri dengan risiko rendah- tinggi untuk bunuh diri. Hasil\npenelitian tersebut didukung oleh Jindal dkk. pada populasi kusta\nyang tinggal di komunitas terpisah menunjukkan bahwa diagnosis\npsikiatri yang tersering adalah distimia, diikuti oleh depresi sedang,\ngangguan cemas menyeluruh, dan skizofrenia (lihat Tabel).\nKomorbiditas ini dipengaruhi oleh usia, status keluarga, durasi\npenyakit, dan ada atau tidaknya deformitas.\nGambar 3. Pola Kelainan Psikiatrik pada penelitian.\nSalah satu hal yang perlu diperhatikan adalah efek samping\npenggunaan obat pada kusta, terutama penggunaan kortikosteroid\ndosis tinggi dan dalam jangka panjang. Dengan lamanya penggunaan\nkortikosteroid, gangguan psikiatri yang sering muncul adalah\ngangguan mood oleh karena gangguan regulasi hormon. Ditambah\ndengan stigma, maka kondisi kejiwaan pasien kusta dapat lebih sulit\nteratasi.\n- 16 -",
    "year": 2019,
    "source_type": "pnpk",
    "score": 0.0,
    "retrieval_method": "hybrid",
    "source_url": "https://kemkes.go.id/app_asset/file_content_download/1701156043656594cb42cf52.71103349.pdf"
  },
  {
    "doc_id": "pnpk-kusta-2019",
    "page": 16,
    "section_slug": "klasifikasi",
    "section_path": "bab_3/klasifikasi",
    "text": "D. Klasifikasi\nBerbagai klasifikasi penyakit kusta dibuat dengan tujuan tertentu,\nnamun yang banyak digunakan adalah klasifikasi menurut WHO dan\nklasifikasi Ridley-Jopling.\n1. Klasifikasi WHO\nUntuk kepentingan pengobatan, WHO pada tahun 1987 membuat\nklasifikasi kusta menjadi 2 tipe, yaitu tipe Pausibasiler (PB) dengan\nsedikit atau tidak ditemukan bakteri dan tipe Multibasiler (MB) dengan\njumlah bakteri yang banyak. Tipe PB menurut WHO adalah tipe TT dan\nBT menurut Ridley dan Jopling, sedangkan tipe MB adalah tipe BB, BL\ndan LL, atau tipe apapun dengan BTA positif.\nPada umumnya pemeriksaan kerokan jaringan kulit untuk\npemeriksaan BTA tidak tersedia di lapangan, maka pada tahun 1995\nWHO mengubah klasifikasi menjadi lebih sederhana berdasarkan\nhitung lesi kulit dan jumlah saraf perifer yang terkena, seperti yang\nterlihat pada tabel 1.\nTabel 1. Klasifikasi klinis kusta menurut WHO (1995)\nSIFAT PB MB\nLesi kulit 1-5 lesi >5 lesi\n(makula, plak, hipopigmentasi/eritema, hipopigmentasi/eritema,\npapul, nodus) distribusi tidak simetris, distribusi lebih simetris,\nhilangnya sensasi jelas hilangnya sensasi kurang\njelas\nKerusakan saraf hanya satu cabang saraf banyak cabang saraf\n(sensasi hilang/\nkelemahan otot\nyang dipersarafi\noleh saraf yang\nterkena)\n2. Klasifikasi Ridley-Jopling\nKlasifikasi kusta menurut Ridley dan Jopling dibuat berdasarkan\ngambaran klinis, bakteriologis, histopatologis dan imunologis menjadi\n5 tipe. Klasifikasi menurut Ridley-Jopling ini lebih ditujukan pada\n- 17 -\npenelitian ketimbang pelayanan, yang lebih sesuai dengan klasifikasi\nWHO. Pembagian 5 tipe tersebut sebagai berikut:\na. TT: Tuberkuloid polar, bentuk yang stabil\nb. BT: Borderline tuberculoid\nc. BB: Mid borderline\nd. BL: Borderline lepromatous\ne. LL: Lepromatosa polar, bentuk yang stabil\nUntuk memudahkan menentukan tipe kusta, berikut ditampilkan\ntabel perbedaan gambaran klinis, bakteriologik dan imunologik\nberbagai tipe kusta (Tabel 2 dan 3).\nTabel 2 Gambaran klinis, bakteriologik, dan imunologik kusta\npausibasilar (PB).\nTUBERKULOID BORDERLINE\nSIFAT\n(TT) TUBERCULOID (BT)\nBentuk lesi Makula saja; Makula dibatasi\nmakula dibatasi infiltrat; infiltrat saja.\ninfiltrat\nJumlah Beberapa atau satu\nSatu, dapat dengan satelit\nbeberapa\nDistribusi Masih asimetris\nPermukaan Asimetris Kering bersisik\nAnestesia Kering bersisik Jelas\nJelas\nBTA Hampir selalu Negatif atau hanya 1+\nnegatif\nTes lepromin Positif kuat (3+) Positif lemah\n- 18 -\nTabel 3. Gambaran klinis, bakteriologik, dan imunologik kusta\nmultibasilar (MB).\nBORDERLINE MID\nLEPROMATOSA\nSIFAT LEPROMATOSA BORDERLINE\n(LL)\n(BL) (BB)\nBentuk lesi Makula; Makula; plak; Plak; dome-\ninfiltrat/ papul shaped\nplak difus; (kubah);\npapul; punched-out\nJumlah nodus\nSukar dihitung,\nTidak masih ada kulit Dapat\nterhitung, tidak sehat dihitung,\nDistribusi ada kulit sehat kulit sehat\njelas ada\nPermukaan Simetris Hampir\nsimetris\nHalus berkilat Asimetris\nBatas Halus berkilat\nAgak kasar,\nAnestesi Tidak jelas agak berkilat\nAgak jelas\nTidak ada Agak jelas\nsampai tidak Tidak jelas\njelas Lebih jelas\nBTA\n• Lesi Banyak (ada Banyak Agak banyak\nkulit globus)\nBanyak (ada Biasanya Negatif\n• Sekret globus) negatif\nhidung\nTes Negatif Negatif Biasanya\nlepromin negatif",
    "year": 2019,
    "source_type": "pnpk",
    "score": 0.0,
    "retrieval_method": "hybrid",
    "source_url": "https://kemkes.go.id/app_asset/file_content_download/1701156043656594cb42cf52.71103349.pdf"
  },
  {
    "doc_id": "pnpk-kusta-2019",
    "page": 18,
    "section_slug": "reaksi-kusta",
    "section_path": "bab_3/reaksi-kusta",
    "text": "E. Reaksi Kusta\nReaksi kusta merupakan episode akut yang timbul di tengah proses\nperjalanan penyakit kusta yang kronis. Patofisiologi reaksi kusta ini belum\ndapat dijelaskan secara pasti, namun proses reaksi kusta dapat\ndigambarkan dengan teori imunologik. Berdasarkan hal tersebut, reaksi\nkusta dibagi menjadi reaksi tipe 1 dan reaksi tipe 2.\nBerikut adalah gambaran tipe reaksi yang terjadi dan hubungannya\ndengan spektrum imunitas dan tipe kusta menurut Ridley-Jopling.\n- 19 -\nGambar 3. Hubungan tipe reaksi dengan klasifikasi menurut Ridley dan\nJopling.\n1. Reaksi tipe 1\nReaksi tipe 1 lebih sering disebut sebagai reaksi reversal. Reaksi\nreversal hanya dapat terjadi pada pasien yang berada dalam spektrum\nborderline (BL, BB, BT), karena tipe borderline ini merupakan tipe tidak\nstabil, sehingga mudah berubah. Pada reaksi reversal, respons imun\nseluler berperan penting, yaitu terjadi peningkatan SIS mendadak. Hal\nini menyebabkan gambaran klinis kusta bergeser kearah tipe\ntuberkuloid. Walaupun belum diketahui dengan pasti faktor pencetus\nterjadinya reaksi, namun diperkirakan proses reaksi ini berhubungan\ndengan reaksi hipersensitivitas tipe lambat. Reaksi biasanya terjadi\npada masa pengobatan MDT 6 bulan pertama.\nGejala klinis yang timbul pada reaksi reversal berupa bertambah\naktifnya sebagian atau seluruh lesi yang sudah ada, disertai\nmunculnya lesi baru dalam waktu yang singkat. Perubahan lesi\nmenjadi aktif dapat digambarkan sebagai perubahan warna lesi\nmenjadi semakin eritem, udem, atau lesi menjadi lebih infiltratif dan\nlebih luas (Gambar 4). Perlu pemantauan kejadian neuritis pada reaksi\nini, karena penting untuk menentukan pilihan terapi selanjutnya.\n- 20 -\nGambar 4. Reaksi kusta tipe 1\n2. Reaksi tipe 2\nReaksi tipe 2 terjadi pada pasien kusta dengan jumlah bakteri sangat\nbanyak, yaitu pada tipe LL dan BL. Reaksi sering disebut sebagai\nreaksi ENL (eritema nodusum leprosum), karena memberikan\ngambaran klinis munculnya nodus di kulit. Berbeda dengan reaksi\nreversal, pada patogenesis ENL yang berperan penting adalah respons\nimun humoral.\nReaksi ENL dapat terjadi sebelum pengobatan, saat pengobatan\nataupun setelah selesai, namun banyak terjadi di tahun kedua\npengobatan MDT. Hal ini terjadi karena pada saat pengobatan, banyak\nkuman M. leprae yang mati, sehingga banyak antigen yang bereaksi\ndengan antibodi dan membentuk kompleks imun. Kompleks imun\nyang terbentuk selanjutnya masuk dalam sirkulasi darah, kemudian\nakan mengendap di berbagai organ tubuh dan menimbulkan gejala,\nantara lain nodus eritem disertai nyeri yang terutama muncul pada\nkulit lengan dan tungkai. (lihat Gambar 5) Gejala ini umumnya\nmenghilang dalam beberapa hari atau beberapa minggu, dan dapat\npula diikuti dengan pembentukan nodus baru, sedangkan nodus lama\nmenjadi keunguan. Gejala klinis pada berbagai organ dapat berbentuk\niridosiklitis, neuritis akut, artritis, limfadenitis, orkitis, serta nefritis\nakut. ENL dapat disertai gejala konstitusi dari ringan sampai berat.\nGambar 5. Reaksi kusta tipe 2\n- 21 -\nPerbedaan reaksi kusta tipe 1 dan 2 dapat dilihat dalam tabel 4.\nberikut ini\nTabel 4. Perbedaan reaksi tipe 1 dan 2.\nNo Gejala Tanda Reaksi Tipe 1 Reaksi Tipe 2\n1 Tipe Kusta Dapat terjadi pada Hanya pada kusta\nkusta tipe PB tipe MB.\nmaupun MB.\n2 Waktu Biasanya segera Biasanya setelah\ntimbulnya setelah mendapatkan\npengobatan.\npengobatan yang\nlama, umumnya\nlebih dari 6 bulan\n3 Keadaan Umumnya baik, Ringan sampai\numum demam ringan (sub- berat disertai\nfebris) atau tanpa kelemahan umum\ndemam. dan demam tinggi.\n4 Peradangan di Sebagian lesi lama Timbul nodus\nmenjadi lebih eritema, lunak dan\nKulit\naktif, eritem, udem,\nnyeri, dan dapat\nberkilat, hangat.\nberulserasi.\nDapat timbul lesi\nBiasanya pada\nbaru.\nlengan dan tungkai.\n5 Saraf Sering terjadi neuritis, Sering terjadi\nberupa nyeri saraf neuritis.\ndan atau gangguan\nfungsi saraf. Kadang\ndidapat kan silent\nneuritis.\n6 Peradangan Anestesi kornea dan Iritis, iridosiklitis,\npada mata lagoftalmos karena glaukoma, katarak\nketerlibatan N.V dan\ndll.\nN.VII\n7 Peradangan Hampir tidak ada. Terjadi pada testis,\npada organ sendi, ginjal,\nlain kelenjar getah\nbening, dll.\n- 22 -\nBerdasarkan berat dan ringannya gejala, reaksi kusta terbagi menjadi\n2 yaitu reaksi ringan dan berat (table 5). Sangat penting bagi tenaga\nkesehatan untuk mengenali gejala reaksi tersebut karena dapat\nmenyebabkan kerusakan saraf tepi. Di samping itu, pengenalan\ntentang berat dan ringannya gejala penting ke layanan kesehatan yang\nlebih lengkap untuk tatalaksana komprehensif.\nTabel 5. Perbedaan reaksi ringan dan berat pada reaksi tipe 1 dan 2\nOrgan Reaksi tipe 1 Reaksi tipe 2\nNo yang\nterkena Ringan Berat Ringan Berat\n1 Kulit Lesi Lesi Nodus, Nodus eritem,\nhipopig hipopigmen- eritem, panas dan\nmentasi tasi menjadi panas nyeri, sering\nmen- eritem; dan menjadi ulkus.\njadi eritem nyeri, Jumlah banyak\neritem; semakin dapat\neritem eritem dan menjadi\nsemakin udem. ulkus.\neritem dan Timbul lesi Jumlah\nsedikit\nudem. baru.\nTidak ada Kadang\nulserasi. disertai\nTidak ada demam\nudem dan\ntangan malaise.\ndan kaki Ulserasi (+)\nEdema\ntangan\ndan kaki (+)\n2 Saraf tepi Membesar, Membesar, Membesar, Membesar, nyeri\ntidak nyeri. nyeri tidak nyeri\nFungsi Fungsi saraf Fungsi Fungsi saraf\nsaraf terganggu saraf terganggu\ntidak tidak\nterganggu terganggu\n- 23 -\n3 Gejala Demam: Demam: (±) Demam: Demam: (+)\nkonstitusi (-) (±)\n4 Gangguan Tidak ada Tidak ada Tidak ada iridosiklitis,\npada orkhitis,nephritis,\norgan lain limfadenitis, dsb\n* Catatan: bila ada reaksi pada lesi kulit yang dekat dengan saraf,\ndikategorikan sebagai reaksi berat",
    "year": 2019,
    "source_type": "pnpk",
    "score": 0.0,
    "retrieval_method": "hybrid",
    "source_url": "https://kemkes.go.id/app_asset/file_content_download/1701156043656594cb42cf52.71103349.pdf"
  },
  {
    "doc_id": "pnpk-kusta-2019",
    "page": 23,
    "section_slug": "diagnosis-dan-pemeriksaan-penunjang",
    "section_path": "bab_3/diagnosis-dan-pemeriksaan-penunjang",
    "text": "F. Diagnosis dan Pemeriksaan Penunjang\n1. Diagnosis\nDiagnosis penyakit kusta ditetapkan berdasarkan temuan satu dari\ntiga tanda kardinal kusta berikut ini, yaitu:\na. Kelainan kulit atau lesi yang khas kusta, dapat berbentuk\nhipopigmentasi atau eritema yang mati rasa (anestesi)\nb. Penebalan saraf perifer disertai dengan gangguan fungsi saraf\nakibat peradangan (neuritis) kronis. Gangguan fungsi saraf ini\ndapat berupa:\n1) Gangguan fungsi sensoris: anestesi\n2) Gangguan fungsi motoris: paresis atau paralisis otot\n3) Gangguan fungsi otonom: kulit kering atau anhidrosis dan\nterdapat fisura\nc. Adanya basil tahan asam (BTA) pada kerokan jaringan kulit (slit\nskin smear).\nUntuk memastikan tanda kardinal pertama, selanjutnya dilakukan\npemeriksaan gangguan sensibilitas pada lesi kulit. Pemeriksaan\ngangguan rasa raba dilakukan dengan menggunakan usapan ujung\nkapas pada lesi. Gangguan terhadap suhu, dapat dilakukan dengan\nmenggunakan dua tabung reaksi berisi air hangat bersuhu 400 C dan\nair dingin. Bila pasien tidak dapat membedakan suhu hangat dan\ndingin, maka telah terjadi gangguan sensibilitas. Gangguan terhadap\nrasa nyeri diperiksa dengan menggunakan ujung jarum. Bila pasien\nmerasakan ujung jarum tersebut tumpul, maka telah terjadi\nhipoestesi. Tetapi bila tidak merasakan sakit, berarti telah terjadi\nanestesi. Untuk mengetahui adanya kerusakan fungsi saraf otonom,\nharus diperhatikan adanya kekeringan kulit di daerah lesi berupa sisik\nhalus. Bila tidak jelas, dapat dilakukan pemeriksaan dengan\n- 24 -\nmenggunakan pensil tinta (tanda Gunawan). Cara pemeriksaan yaitu\ndengan menggores kulit menggunakan pensil tersebut mulai dari\ntengah lesi ke arah kulit normal. Bila ada gangguan, maka goresan\npada kulit normal akan lebih tebal bila dibandingkan dengan bagian\ntengah lesi, karena goresan pinsil lumer karena adanya keringat.\nDapat pula diperhatikan adanya alopesia di daerah lesi, yang lebih\nmudah terlihat bila rambut yang tumbuh cukup lebat. Gangguan\nfungsi motoris menyebabkan kelainan otot, atrofik atau paresis, dan\ndapat diperiksa dengan Voluntary Muscle Test (VMT). Pada dasarnya,\nsebagian besar pasien dapat di diagnosis dengan pemeriksaan klinis.\nApabila hanya ditemukan tanda kardinal kedua, perlu dirujuk ke\ndokter saraf atau dokter spesialis kulit, dengan sarana pemeriksaan\npenunjang yang memadai. Jika masih ragu maka dianggap sebagai\npenderita yang dicurigai atau tersangka (suspek).\n- 25 -\nTanda-tanda tersangka kusta yang perlu diwaspadai ialah:\na. Tanda-tanda pada kulit\n1) Lesi kulit yang eritema atau hipopigmentasi (gambaran yang\npaling sering ditemukan), datar atau menimbul\n2) Lesi hipoestesi atau anestesi\n3) Lesi yang tidak gatal\n4) Anestesi atau parestesi pada tangan dan kaki\n5) Adanya kelainan kulit yang tidak berkeringat (anhidrosis),\nmengkilap atau kering bersisik, dan atau alis mata tidak\nberambut (madarosis).\n6) Bengkak atau penebalan pada wajah dan cuping telinga\n7) Lepuh tidak nyeri pada tangan dan kaki\nb. Tanda-tanda pada saraf :\n1) Nyeri tekan dan atau spontan pada saraf\n2) Rasa kesemutan, tertusuk-tusuk, dan nyeri pada anggota\ngerak\n3) Kelemahan anggota gerak dan atau kelopak mata\n4) Pembesaran saraf\n5) Adanya cacat (disabilitas, deformitas)\n6) Luka (ulkus) yang sulit sembuh\nc. Lahir dan tinggal di daerah endemik kusta dan mempunyai\nkelainan kulit yang tidak sembuh dengan pengobatan rutin,\nterutama bila terdapat keterlibatan saraf tepi\nd. Tanda-tanda pada Mata\nInspeksi dilakukan pada ruangan yang agak gelap dengan\nmenggunakan lampu senter dan kaca pembesar. Pemeriksaan\ndasar yang dapat dilakukan dokter umum atau dokter bukan\nspesialis mata adalah sebagai berikut:\n1) Pemeriksaan lesi di daerah wajah\n2) Pemeriksaan tajam penglihatan\n3) Pemeriksaan tekanan bola mata dengan palpasi\n4) Fungsi kelopak mata\na) Laju berkedip\nNormal setiap 15-25 detik dengan penilaian: komplit/tidak,\nsimetris/asimetris\n- 26 -\nb) Fungsi kelopak mata dinilai dengan: dapat menutup\ndengan sempurna atau tidak.\nc) Mata ditutup perlahan dan dipertahankan selama 10\ndetik, lalu jarak antara kelopak mata atas dan bawah\ndiukur dengan penggaris.\nd) Mata ditutup dengan kuat dan dipertahankan selama\n10 detik lalu jarak antara kelopak mata atas dan bawah\ndiukur dengan penggaris.\ne) Deformitas kelopak\n5) Sekret mata\nPenilaian ada tidaknya sekret dilaukan dengan atau tanpa\npenekanan pada kantung air mata.\n6) Kemerahan pada mata.\nDiagnosis kemerahan pada mata dapat dilihat pada tabel 6.\nTabel 6. Kemerahan pada mata\nKonjungtivitis Keratitis Uveitis\nVisus Normal ↓ ↓\nHiperemis Konjungtiva Perikornea Siliar\nSekret + - -\nFotofobia - + +\nPalpebra Normal Normal Normal\nKornea Jernih Bercak Infiltrat Sel radang (+)\nBilik mata depan Normal Hipopion (+)/(-) Hipopion (+)/(-)\nIris Normal Normal Sinekia\nPupil Normal Normal Miosis\nLensa Normal Normal Sel radang (+)\n- 27 -\n7) Kornea\na) Permukaan kornea diperiksa dengan memberikan sinar\ndari arah depan dengan senter dengan lup untuk\nmelihat ada tidaknya defek, infiltrate, atau kekeruhan.\nb) Pemeriksaan sensibilitas kornea dengan menggunakan\nujung kapas yang disentuhkan sekitar daerah lesi\nkornea yang terkena untuk menilai fungsi sensoris\nkornea.\n8) Bilik mata depan\nPemeriksaan bilik mata depan dengan menggunakan senter\ndan lup untuk mencari adanya nanah yang membentuk “air-\nfluid level” dalam bilik mata depan. Hipopion merupakan\nkumpulan sel radang di bilik mata depan.\n9) Pupil\nPemeriksaan dilakukan di ruangan redup menggunakan\nsenter dan lup yang digerakkan dari arah samping mata\ndengan cepat ke arah pupil. Perhatikan reflex pupil, ukuran,\ndan bentuk.\n10) Iris\nPerhatikan ada tidaknya atrofi atau kerusakan iris,\nperlengketan iris di lensa (sinekia posterior), dan di kornea\n(sinekia anterior).\n11) Lensa\nPerhatikan ada tidaknya kekeruhan lensa (katarak).\n- 28 -\nTanda-tanda tersebut merupakan tanda-tanda tersangka kusta dan\nbelum dapat digunakan sebagai dasar diagnosis penyakit kusta. Jika\ndiagnosis kusta masih belum dapat ditegakkan, tindakan yang dapat\ndilakukan adalah:\na. Pikirkan kemungkinan penyakit kulit lain (seperti panu, kurap,\nkudis, psoriasis, vitiligo)\nb. Pengambilan kerokan jaringan kulit untuk pemeriksaan BTA\nc. Bila tidak ada petugas terlatih dan tidak tersedia sarana\npemeriksaan kerokan jaringan kulit, tunggu 3-6 bulan dan\nperiksa kembali adanya tanda utama. Jika ditemukan tanda\nutama, diagnosis kusta dapat ditegakkan. Bila masih meragukan,\npasien tersangka harus dirujuk.\nPerlu diingat bahwa tanda-tanda utama tersebut dapat tetap\nditemukan pada pasien yang sudah sembuh atau release from\ntreatment (RFT). Anamnesis yang teliti perlu dilakukan untuk\nmenghindari pengobatan ulang yang tidak perlu.\n2. Pemeriksaan Penunjang\nBila tersedia laboratorium untuk pemeriksaan penunjang maka dapat\ndilakukan pemeriksaan BTA, histopatologi dan serologi.\na. Bakterioskopis\nPemeriksaan ini dilakukan untuk membantu menegakan\ndiagnosis serta pilihan pengobatan. Pemeriksaan dimulai dengan\nmembuat kerokan jaringan kulit yang kemudian diwarnai\nmenggunakan pewarnaan terhadap basil tahan asam (BTA),\ncontohnya dengan Ziehl- Neelsen.\nHal pertama yang penting adalah penentuan lesi sebagai\nspesimen yang akan diperiksa, yaitu lesi yang diduga memiliki\nkuman M. leprae paling padat. Untuk pemeriksaan rutin,\numumnya dilakukan minimal pada 4-6 tempat, yaitu pada cuping\ntelinga bagian bawah serta lesi lain yang terlihat paling\neritematosa dan infiltratif.\nPengambilan bahan dilakukan dengan bantuan scalpel steril pada\nlesi yang telah didesinfeksi dan dijepit dengan ibu jari dan\ntelunjuk hingga iskemi. Irisan dibuat sampai dermis dan melewati\n- 29 -\nsubepidermal clear zone agar dapat mengambil jaringan yang\nbanyak mengandung sel Virchouw (mengandung kuman M.\nleprae). Kemudian kerokan dioleskan pada gelas alas, difiksasi di\natas api bunsen, dan diwarnai menggunakan pewarnaan tahan\nasam, yaitu Ziehl Neelsen.\nBerbeda dengan sediaan jaringan sebelumnya, pada sediaan\nmukosa hidung, dilakukan nose blows. Sekret hidung ditampung\npada sehelai plastik, dan waktu yang terbaik adalah pagi hari.\nSediaan kemudian dioleskan pada gelas alas menggunakan kapas\nlidi, dan dilakukan fiksasi serta pewarnaan. Selain itu,\npengambilan spesimen dari mukosa hidung dapat berupa\nkerokan mukosa dengan menggunakan scalpel tumpul, atau\nusapan (swab) dengan kapas lidi.\nPada pewarnaan basil tahan asam, kuman M. leprae akan\nmenunjukan bentuk batang utuh (solid), batang terputus (\nfragmented), dan butiran (granular). Bentuk solid\nmenggambarkan keadaan kuman hidup sedangkan nonsolid\nmenggambarkan keadaan kuman mati. Hal ini menjadi penting\nkarena kuman yang berbentuk solid, adalah kuman hidup yang\ndapat berkembang biak, serta dapat menularkan pada orang lain.\nKepadatan BTA tanpa melihat bentuk solid dan non solid dapat\ndijelaskan menggunakan Indeks Bakteri (IB). Menurut Ridley,\nrentang IB dimulai dari angka 0 hingga 6+, dengan 0 berarti tidak\nada BTA dalam 100 lapang pandang (LP)\n1) 1+ bila 1-10 BTA dalam 100 LP\n2) 2+ bila 1-10 BTA dalam 10 LP\n3) 3+ bila 1-10 BTA rata-rata dalam 1 LP\n4) 4+ bila 11-100 BTA rata-rata dalam 1 LP\n5) 5+ bila 101-1000 BTA rata-rata dalam 1 LP\n6) 6+ bila > 1000 BTA rata-rata dalam 1 LP\nPenilaian dilanjutkan dengan perhitungan indeks morfologi\n(IM) yaitu persentase basil yang hidup, sebagai berikut:\nRumus:\n𝐽𝐽𝐽𝐽𝐽𝐽𝐽𝐽𝐽𝐽ℎ 𝑠𝑠𝑠𝑠𝐽𝐽𝑠𝑠𝑠𝑠\nx 100%\n𝐽𝐽𝐽𝐽𝐽𝐽𝐽𝐽𝐽𝐽ℎ 𝑠𝑠𝑠𝑠𝐽𝐽𝑠𝑠𝑠𝑠 +𝑛𝑛𝑠𝑠𝑛𝑛𝑠𝑠𝑠𝑠𝐽𝐽𝑠𝑠𝑠𝑠\n- 30 -\nb. Histopatologis\nHistiosit merupakan bentuk makrofag yang berada di kulit dan\nbeperan dalam proses fagositosis. Proses ini ditentukan oleh\nsistem imun seluler (SIS) orang tersebut. Pada orang dengan SIS\ntinggi, histiosit akan berpindah ke tempat kuman berada dan\nterlibat proses imunologik dengan adanya faktor kemotaktik. Sisa\nmakrofag yang berlebihan saat kuman sudah di fagosit akan\nberubah menjadi sel epiteloid yang tidak bergerak. Adanya masa\nepiteloid dalam jumlah banyak yang dikelilingi limfosit akan\nmembentuk tuberkel yang selanjutnya akan merusak jaringan.\nSehingga ditemukan gambaran histologik pada tipe tuberkuloid\nyaitu berupa tuberkel serta diikuti dengan kerusakaan saraf,\ntanpa adanya kuman atau hanya dalam jumlah yang sedikit.\nSedangkan pada orang dengan SIS yang rendah atau lumpuh,\nhistiosit tidak mampu menghancurkan kuman, dan bahkan\ndijadikan tempat berkembang bakteri M.leprae, yang selanjutnya\ndisebut dengan sel Virchow atau sel lepra atau sel busa. Pada tipe\nlepromatosa, ditemukan area di bawah epidermis yang bebas\nradang, disebut supepidermal clear zone. Selain itu ditemukan\nbanyak sel Virchow pada tipe ini.\nc. Serologi\nPemeriksaan serologi dilakukan dengan mengamati keberadaan\nantibodi pada orang yang terinfeksi M. leprae. Beberapa antibodi\nspesifik dapat diperiksa, seperti antibody anti phenolic glycolipid-\n1 (PGL-1) serta antiprotein 16 kD dan 53 kD. Selain itu didapati\npula antibodi nonspesifik seperti antibodi anti-lipoarabinomaan\n(LAM). Antibodi tersebut akan dideteksi dengan menggunakan\nbeberapa macam pemeriksaan, seperti: uji MLPA (Mycobacterium\nLeprae Particle Aglutination), ELISA (Enzyme Linked\nImmunosorbent Asay), ML dipstick (Mycobacterium leprae dipstick)\ndan ML flow (Mycobacterium leprae flow test).\nd. Lain-lain\nPenegakan diagnosis PNL sangat sulit, sehingga seringkali\nterdiagnosis setelah terjadi kecatatan. Untuk menegakkan\ndiagnosis PNL, dibutuhkan modalitas tambahan yaitu\npemeriksaan elektrofisiologi, biopsi saraf, dan fine needle\n- 31 -\naspiration cytology. Pada pemeriksaan elektrofisiologi, yang\nbanyak dijumpai adalah gambaran neuropati sensorik tipe\naksonal dan/atau neuropati motorik tipe campuran (aksonal dan\ndemielinisasi) dengan pemanjangan latensi, penurunan\namplitudo dan kecepatan hantar saraf.\nBiopsi saraf dapat memberikan hasil yang cukup konklusif, yaitu\nditemukannya kuman BTA atau nekrosis kaseosa. Bila BTA tidak\nditemukan, gambaran berupa infiltrat mononuklear perineural\ndan endo\nneural juga mengarah kepada neuritis akibat kusta. Namun,\ntindakan ini dapat menimbulkan komplikasi berupa cedera saraf\ndan memperberat disabilitas. Fine needle aspiration cytology pada\nsaraf yang terlibat dapat membantu penegakan diagnosis melalui\nprosedur yang lebih tidak invasif. Polymerase chain reaction (PCR)\njuga dapat dilakukan untuk mendeteksi DNA M. leprae dari\nspesimen biopsi.\n3. Diagnosis Banding\nKusta disebut sebagai the greatest imitator, karena secara klinis\nmenyerupai berbagai penyakit kulit lain. Beberapa kelainan kulit yang\nmirip dengan penyakit kusta, antara lain:\na. Lesi eritem bersisik: psoriasis, pitiriasis rosea, dermatitis\nseboroik, dermatofitosis\nb. Lesi hipopigmentasi atau hiperpigmentasi tanpa skuama: vitiligo,\nbirth marks.\nc. Lesi hipopigmentasi dengan skuama halus: pitirasis versikolor,\npitiriasis alba\nd. Papul, plak atau nodul: neurofibromatosis, sarkoma kaposi,\nveruka vulgaris, leukemia kutis, granuloma anulare,\ntuberculosis kutis verukosus, xanthomatosis.\n- 32 -\nBerbagai diagnosis banding penyakit kusta dapat dilihat pada\ngambar berikut (Gambar 6 hingga 12).\nDiagnosis banding: lesi eritema dan berskuama\nGambar 6. Psoriasis Gambar7.Tinea Sirsinata\nLesi plak eritema berbatas tegas, Lesi eritema, vesikel dan krusta.\nskuama berlapis.\nDiagnosis banding: bercak putih/hipopigmenasi\nGambar 8. Vitiligo Gambar 9 Pitiriasis Versikolor\nPigmen kulit hilang total, Lesi berupa bercak\nwarna kulit amat putih, batas hipopigmentasi dengan skuama\ntegas. halus.\nDiagnosis banding: nodul\n- 33 -\nGambar 3.10 Neurofibromatosis Gambar 3.11 Sarkoma kaposi\nBercak café au lait ( bercak coklat Nodus lunak berwarna biru keunguan,\nbatas tegas) yang muncul sejak lahir. lokalisata (terutama pada kaki).\nNodus dan tumor bertangkai pada usia Pemeriksaan BTA (-)\nyang lebih lanjut, tersebar luas tanpa rasa\nbaal. Pemeriksaan BTA (-)\nGambar 3.12. Veruka vulgaris\nPapul-papul dengan permukaan kasar (verukosa)",
    "year": 2019,
    "source_type": "pnpk",
    "score": 0.0,
    "retrieval_method": "hybrid",
    "source_url": "https://kemkes.go.id/app_asset/file_content_download/1701156043656594cb42cf52.71103349.pdf"
  },
  {
    "doc_id": "pnpk-kusta-2019",
    "page": 33,
    "section_slug": "disabilitas-pada-kusta",
    "section_path": "bab_3/disabilitas-pada-kusta",
    "text": "G. Disabilitas Pada Kusta\nPada penyakit kusta, hendaya dapat terjadi pada beberapa organ\nseperti kaki, tangan, dan mata. Keadaan tersebut diawali dengan adanya\nkerusakan saraf yang berbentuk nyeri saraf, sensibilitas yang hilang, dan\nkekuatan otot motorik yang berkurang. Terdapat 2 jenis hendaya, yaitu\nprimer dan sekunder.\nHendaya primer adalah kerusakan yang disebabkan oleh aktivitas\nlangsung bakteri M. leprae terhadap jaringan. Beberapa contoh dari\nhendaya primer, yaitu anestesi, kulit kering, dan claw hand. Pada hendaya\nsekunder, gangguan yang timbul terjadi akibat keadaan hendaya primer\nyang tidak ditangani ataupun gagal di koreksi. Sebagai contoh yaitu ulkus\ndan kontraktur. Hendaya kusta dapat terjadi melalui 2 proses, yaitu:\n- 34 -\n1. Infiltrasi M.leprae secara langsung terhadap susunan saraf tepi dan\norgan\n2. Proses reaksi kusta.\nUntuk memudahkan pemahaman terjadinya hendaya kusta, berikut\nini dapat dilihat bagan gangguan fungsi saraf tepi (Gambar 13).\nGambar 13. Gangguan Fungsi Saraf Perifer\n1. Patogenesis Disabilitas\nGejala yang timbul bermula dari keluhan hilangnya sensibilitas atau\ntimbul rasa nyeri. Pasien kerap menyadari ada luka atau lepuh yang\ntidak nyeri, ini terjadi karena aliran darah terganggu dan berlangsung\nlama. Kemudian pasien juga dapat mengeluhkan berkurangnya\nkekuatan otot sehingga mengganggu aktivitas sehari-hari, seperti\nkesulitan memegang benda kecil, memegang kancing baju dan\nmengancingkannya, hingga kesulitan dalam berjalan. Berbagai\nkelainan yang timbul akibat kerusakan saraf dapat dilihat pada tabel\n3.7 berikut ini.\n- 35 -\nTabel 7. Kelainan yang timbul akibat gangguan fungsi saraf\nSaraf Motorik Sensorik Otonom\nFasialis Kelopak mata Kelenjar\ntidak menutup keringat,\nminyak\ntidak\nberfungsi:\nkulit\nkering\ndan retak.\nAliran\ndarah\nterganggu\nUlnaris Clawing jari Anestesi telapak\nkelingking dan tangan sisi lateral,\njari manis jari manis dan\nkelingking\nMedianus Clawing ibu jari, Anestesi telapak\ntelunjuk, dan jari tangan bagian ibu\ntengah jari telunjuk dan\njari tengah\nRadialis Wrist drop\nPeroneus Foot drop\nTibialis Claw toes Anestesi telapak\nposterior kaki\n2. Klasifikasi Disabilitas Kusta\nSaat ini istilah disabilitas lebih dianjurkan ketimbang kecacatan.\nDisabilitas memiliki arti luas, sehingga perlu dibedakan berdasarkan\ntingkatnya. Menurut WHO, disabilitas kusta dinilai dari gejala\nkerusakan fungsi serta struktur dari organ mata, tangan dan kaki.\nMasing-masing organ memiliki tingkat disabilitas masing-masing yang\nditandai dengan angka antara 0 hingga 2. Angka disabiltas tertinggi\nyang dimiliki pasien akan menjadi tingkat disabilitas pasien tersebut\n(tingkat disabilitas umum). Berikut dapat dilihat tingkat disabilitas\nkusta menurut WHO yang telah dilakukan amandemen pada 7th WHO\nExpert Committee on Leprosy, 1997.\n- 36 -\nTabel 8. Tingkat Disabilitas kusta menurut WHO\nTingkat Mata Telapak tangan/kaki\n0 Tidak ada kelainan pada Tidak ada cacat akibat kusta\nmata (termasuk visus)\n1 Ada kelainan pada mata, Anestesi, kelemahan otot\ntetapi tidak terlihat (Tidak ada cacat/kerusakan\n(anestesi kornea), visus yang kelihatan akibat kusta)\nsedikit berkurang\n2 Ada kelainan mata yang Ada cacat/kerusakan yang\nterlihat (misalnya kelihatan akibat kusta.\nlagoftalmus, kekeruhan Misalnya ulkus, jari kiting,\nkornea, iridosiklitis) dan kaki semper.\natau visus sangat\nterganggu / berat (visus\n<6/60)\nDi Indonesia, terdapat keterbatasan pemeriksaan mata di lapangan,\nsehingga dibuat modifikasi klasifikasi tingkat disabilitas sesuai\nkeadaan tersebut, seperti tertera pada tabel berikut:\nTabel 9. Modifikasi Tingkat Disabilitas Kusta di Lapangan\nTingkat Mata Telapak tangan/kaki\n0 Tidak ada kelainan pada Tidak ada cacat akibat kusta\nmata akibat kusta\n1 Tidak dilakukan Anestesi, kelemahan otot\npemeriksaan lapangan Tidak ada cacat/kerusakan\nyang keliatan akibat kusta\n2 Ada lagoftalmos Ada cacat/kerusakan yang\nkeliatan akibat kusta.\nMisalnya ulkus, jari kriting,\nkaki semper.\nDari uraian diatas, maka tingkat disabilitas dapat dijelaskan sebagai\nberikut :\na. Disabilitas tingkat 0: tidak ditemukan disabilitas\nb. Disabilitas tingkat 1: disabilitas yang disebabkan oleh kerusakan\nsaraf sensorik yang tidak terlihat, seperti hilangnya rasa raba\npada kornea mata, telapak tangan dan telapak kaki, dan saraf\nmotorik yang mengakibatkan kelemahan otot tangan dan kaki.\nc. Gangguan fungsi sensorik pada mata tidak di periksa di lapangan,\noleh karena itu tidak ada disabilitas tingkat 1 pada mata\nd. Disabilitas tingkat satu pada telapak kaki berisiko terjadinya\nulkus plantaris, namun dengan perawatan diri secara rutin hal\nini dapat di cegah\n- 37 -\ne. Mati rasa pada lesi bukan merupakan cacat tingkat 1, karena\nbukan disebabkan oleh kerusakan saraf perifer utama, tetapi\ndisebabkan rusaknya cabang saraf kecil pada kulit\nf. Oleh karena itu, mencatat tingkat kecacatan merupakan tindakan\npenting untuk mencegah kerusakan lebih lanjut.\ng. Disabilitas tingkat 2 berarti kerusakan yang terlihat.\n1) Untuk mata :\na) Tidak mampu menutup mata dengan rapat (lagoftalmos)\nb) Kekeruhan kornea\nc) Kemerahan yang jelas pada mata (terjadi pada ulserasi\nkornea atau uveitis)\nd) Gangguan penglihatan berat atau kebutaan.\n2) Untuk tangan dan kaki :\na) Luka dan ulkus di telapak\nb) Deformitas yang disebabkan oleh kelumpuhan otot (kaki\nsemper atau jari kontraktur) dan atau hilangnya\njaringan (atrofi) atau reabsorbsi parsial dari jari-jari.",
    "year": 2019,
    "source_type": "pnpk",
    "score": 0.0,
    "retrieval_method": "hybrid",
    "source_url": "https://kemkes.go.id/app_asset/file_content_download/1701156043656594cb42cf52.71103349.pdf"
  },
  {
    "doc_id": "pnpk-kusta-2019",
    "page": 37,
    "section_slug": "tata-laksana",
    "section_path": "bab_3/tata-laksana",
    "text": "H. Tata laksana\n1. Farmakologis\na. Multi drug therapy\nTahun 1995 WHO merekomendasikan pengobatan kusta dengan\nMulti Drug Therapy (MDT) untuk tipe PB maupun MB.\nTujuan pengobatan adalah:\n1) Memutuskan mata rantai penularan\n2) Mencegah resistensi obat\n3) Memperpendek masa pengobatan\n4) Meningkatkan keteraturan berobat\n5) Mencegah terjadinya cacat atau mencegah bertambahnya\ncacat yang sudah ada sebelum pengobatan.\nRegimen pengobatan MDT\nMulti Drug Therapy (MDT) adalah kombinasi dua atau lebih obat\nanti kusta, salah satunya rifampisin sebagai anti kusta yang\nbersifat bakterisidal kuat sedangkan obat anti kusta lain bersifat\nbakteriostatik. Obat MDT tersedia dalam bentuk blister untuk\npasien dewasa dan anak berusia 10-14 tahun.\n- 38 -\nBerikut ini merupakan kelompok orang yang membutuhkan MDT:\n1) Pasien yang baru didiagnosis kusta dan belum pernah\nmendapat MDT.\n2) Pasien ulangan, yaitu pasien yang mengalami hal-hal di\nbawah ini:\na) Relaps\nb) Masuk kembali setelah putus obat/default (dapat PB\nmaupun MB)\nc) Pindah berobat (pindah masuk)\nd) Ganti klasifikasi/tipe.\nRejimen pengobatan MDT di Indonesia sesuai dengan yang\ndirekomendasikan oleh WHO, sebagai berikut:\n1) Pasien pausibasiler (PB) dewasa\nPengobatan bulanan: hari pertama (obat diminum di depan\npetugas)\na) 2 kapsul rifampisin @ 300 mg (600 mg)\nb) 1 tablet dapson/DDS 100 mg\nPengobatan harian : hari ke-2 hingga 28.\nc) 1 tablet dapson/DDS 100 mg\nSatu blister untuk 1 bulan. Dibutuhkan 6 blister yang\ndiminum selama 6-9 bulan.\n2) Pasien multibasiler (MB) dewasa\nPengobatan bulanan: hari pertama (obat diminum di depan\npetugas)\na) 2 kapsul rifampisin @ 300 mg (600 mg)\nb) 3 tablet lampren @ 100 mg (300 mg)\nc) 1 tablet dapson/DDS 100 mg\nPengobatan harian: hari ke-2 hingga 28\nd) 1 tablet lampren 50 mg\ne) 1 tablet dapson/DDS 100 mg.\nSatu blister untuk 1 bulan. Dibutuhkan 12 blister yang\ndiminum selama 12-18 bulan.\n3) Dosis MDT PB untuk anak (umur 10-14 tahun)\nPengobatan bulanan: hari pertama (obat diminum di depan\npetugas)\na) 2 kapsul rifampisin 150 mg dan 300 mg\n- 39 -\nb) 1 tablet dapson/DDS 50 mg\nPengobatan harian: hari ke-2 hingga 28\nc) 1 tablet dapson/DDS 50 mg.\nSatu blister untuk 1 bulan. Dibutuhkan 6 blister yang\ndiminum selama 6-9 bulan.\n4) Dosis MDT MB untuk anak (umur 10-14 tahun)\nPengobatan bulanan: hari pertama (obat diminum di depan\npetugas)\na) 2 kapsul rifampisin 150 mg dan 300 mg\nb) 3 tablet lampren @ 50 mg (150 mg)\nc) 1 tablet dapson/DDS 50 mg\nPengobatan harian: hari ke-2 hingga 28:\nd) 1 tablet lampren 50 mg selang sehari\ne) 1 tablet dapson/DDS 50 mg\nSatu blister untuk 1 bulan. Dibutuhkan 12 blister yang\ndiminum selama 12-18 bulan.\nPada pasien anak berusia kurang dari 10 tahun, dosis\ndisesuaikan dengan berat badan, sebagai berikut:\n1) Rifampisin: 10-15 mg/kgBB\n2) Dapson : 1-2 mg/kgBB\n3) Lampren : 1 mg/kgBB\nSebagai pedoman praktis untuk dosis MDT bagi pasien kusta.\nDapat dilihat pada tabel 10.\nTabel 10. Dosis MDT pada pasien kusta tipe PB\nJenis Obat 10-<15 ≥ 15 tahun\nKeterangan\ntahun (Anak) (Dewasa)\nRifampisin 450 mg/bln 600 mg/bln Minum di depan\npetugas\nDapson 50 mg/bln 100 mg/bln Minum di depan\n(DDS) petugas\n50 mg/hari 100 mg/hari Minum di rumah\n* Sesuaikan dosis bagi anak dengan usia yang lebih kecil dari 10\ntahun. Misalnya, dapson 25mg/hari dan rifampisin 300 mg/bulan\n(diawasi).\n- 40 -\nTabel 11. Dosis MDT pada pasien kusta tipe MB\n10-<15\n≥ 15 tahun\nJenis Obat tahun Keterangan\n(Dewasa)\n(Anak)\nMinum di\nRifampisin 450 mg/bln 600 mg/bln\ndepan petugas\nMinum di\n50 mg/bln 100 mg/bln\ndepan petugas\nDapson\n(DDS)\nMinum di\n50 mg/hari 100 mg/hari\nrumah\nMinum di\n150 mg/bln 300 mg/bln\ndepan petugas\nKlofazimin\n50 mg Minum\n50 mg/hari\nsetiap 2 hari dirumah\n* Sesuaikan dosis bagi anak yang berusia < 10 tahun. Misalnya,\ndapson 25mg/hari dan rifampisin 300 mg/bulan (diawasi).\nKlofazimin 50 mg 2 kali seminggu, dan Klofazimin 100 mg/bulan\n(diawasi).\nGambar 14. Gambar kemasan (blister)\nBlister PB\nDewasa Anak-anak\nBlister MB\nDewasa Anak-anak\n- 41 -\nb. Pengobatan pada kondisi khusus\n1) Pengobatan kusta pada masa kehamilan dan menyusui\nKusta dapat mengalami eksaserbasi selama kehamilan,\nsehingga penting untuk tetap melanjutkan terapi MDT\nselama kehamilan. The Action Programme for the Elimination\nof Leprosy, WHO, Geneva, telah menentukan bahwa rejimen\nMDT standar adalah aman untuk ibu dan janin, sehingga\nditeruskan tanpa perubahan apapun selama kehamilan.\nSejumlah kecil obat-obatan antikusta diekskresikan melalui\nair susu, namun tidak ada bukti efek samping kecuali\nperubahan warna kulit ringan pada anak yang disebabkan\nklofazimin. Pengobatan dosis tunggal untuk pasien PB lesi\ntunggal sebaiknya ditangguhkan hingga setelah kelahiran.\n2) Pengobatan pasien dengan tuberkulosis aktif\nJika pasien menderita kusta dan tuberkulosis, sangatlah\npenting untuk mengobati keduanya pada waktu yang\nbersamaan. Berikan antituberkulosis yang pantas, sebagai\ntambahan terapi antikusta multiobat sesuai dengan tipe\nkusta nya. Rifampisin adalah lazim untuk kedua rejimen dan\nharus diberikan sesuai dengan dosis tuberkulosis.\n3) Pengobatan pasien dengan infeksi HIV\nTata laksana pasien kusta dengan infeksi HIV sama dengan\npasien lainnya. Informasi yang tersedia sejauh ini\nmengindikasikan bahwa respon pasien terhadap MDT mirip\ndengan pasien kusta dan manajemen lainnya, termasuk\nreaksi, sehingga tidak memerlukan modifikasi.\n4) Pasien yang tidak dapat menggunakan rifampisin\nRejimen pengobatan khusus dibutuhkan pada pasien\nindividual, yang tidak mampu menerima rifampisin karena\nalergi atau penyakit yang menyertai, seperti hepatitis kronik,\natau pada kusta resisten terhadap rifampisin.\nPada 1997, WHO Expert Committee on Leprosy\nmerekomendasikan rejimen 24 bulan berikut untuk pasien\ndewasa dengan kusta MB, yang tidak mampu menerima\nrifampisin terlihat pada tabel 12.\n- 42 -\nTabel 12. Pengobatan MB pada Pasien yang tidak dapat menggunakan\nRifampisin.\nLama\nObat Dosis\npengobatan\nKlofazimin 50 mg/ hari\n6 bulan Ofloksasin 400 mg/ hari\nMinosiklin 100 mg/ hari\nDilanjutkan dengan\nKlofazimin 50 mg/ hari\nDAN\n18 bulan Ofloksasin 400 mg/ hari\nATAU\nMinosiklin 100 mg/ hari\nCatatan:\nPemberian harian klaritromisin 500 mg dapat menggantikan rejimen\ndiatas untuk ofloksasin atau minosiklin selama pengobatan 6 bulan\npertama, bagi pasien MB yang tidak dapat mengonsumsi rifampisin.\n5) Pasien yang menolak klofazimin\nPasien dengan kusta MB yang menolak klofazimin karena\nperubahan warna kulit, tetap membutuhkan pengobatan\nalternatif yang aman dan efektif. Pada pasien seperti ini,\nklofazimin pada terapi MDT normal 12 bulan dapat diganti\ndengan:\na) Ofloksasin, 400 mg/ hari selama 12 bulan, ATAU\nb) Minosiklin, 100 mg/ hari selama 12 bulan\nPada 1997, WHO Expert Committee on Leprosy juga\nmerekomendasikan rejimen alternatif pengobatan MDT\nselama 24 bulan (3 obat) untuk pasien dewasa dengan kusta\nMB, yang menolak klofazimin:\na) Rifampisin, 600 mg setiap bulan selama 24 bulan\nb) Ofloksasin, 400 mg setiap bulan selama 24 bulan, dan\nc) Minosiklin, 100 mg setiap bulan selama 24 bulan\n- 43 -\n6) Pasien yang tidak dapat mengonsumsi Dapson\nPasien yang tidak dapat mengonsumsi dapson dapat\ndisebabkan alergi obat (hipersensitivitas terhadap dapson/\nsindrom dapson) dan anemia hemolitik. Dapson\nmemproduksi efek toksik berat pada pasien kusta manapun,\nbaik kusta PB maupun MB, maka obat tersebut harus segera\ndihentikan. Tidak ada modifikasi rejimen pada pasien dengan\nkusta MB. Namun, klofazimin dengan dosis yang digunakan\npada terapi standar untuk kusta MB harus menggantikan\ndapson dalam rejimen pada kusta PB selama 6 bulan.\nRejimen MDT 6 bulan untuk pasien kusta PB, yang tidak\nmampu menerima dapson, terlihat pada table 13.\nTabel 13. Pengobatan MB yang tidak dapat mengonsumsi dapson\nRifampisin Klofazimin\n600 mg 50 mg setiap hari dan\nDewasa Diberikan satu kali 300 mg satu kali setiap\n50-70 kg setiap bulan, dibawah bulan, dibawah pengawasan\npengawasan\nAnak 450 mg 50 mg diberikan selang\n10-14 Diberikan satu kali seling dan\ntahun setiap bulan, dibawah 150 mg satu kali setiap\npengawasan bulan, dibawah pengawasan\n7) Kondisi khusus lainnya\nKadangkala reaksi kusta (baik tipe 1 atau tipe 2) dengan atau\ntanpa neuritis, dapat terjadi setelah pasien menyelesaikan\npengobatan MDT. Pasien seperti ini harus diobati dengan\nkortikosteroid oral. Sementara itu kortikosteroid diketahui\ndapat mempercepat multiplikasi organisme yang terletak di\nfokus dorman dan mungkin menyebabkan reaktivasi\ndiseminata atau relaps. Namun, terjadinya risiko relaps pada\npasien sangat kecil. Oleh karena itu, direkomendasikan\npemberian klofazimin 50 mg per hari sebagai profilaksis, jika\ndurasi pemberian kortikosteroid diperkirakan melebihi 4\n- 44 -\nminggu. Pemberian klofazimin tetap dilanjutkan hingga\nterapi kortikosteroid dihentikan.\nc. Tata Laksana Reaksi Kusta\nSebelum memulai penanganan reaksi, terlebih dulu lakukan\nidentifikasi tipe reaksi yang dialami serta derajat reaksinya. Hal\nini dapat dinilai dari hasil kesimpulan pemeriksaan pada formulir\npencatatan pencegahan cacat (POD), seperti:\na) Adanya lagoftalmos baru terjadi dalam 6 bulan terakhir\nb) Adanya nyeri raba saraf tepi\nc) Adanya kekuatan otot berkurang dalam 6 bulan\nterakhir\nd) Adanya rasa raba berkurang dalam 6 bulan terakhir\ne) Adanya bercak pecah atau nodul pecah\nf) Adanya bercak aktif (meradang) di atas lokasi saraf tepi\nBila terdapat salah satu dari gejala di atas berarti ada reaksi berat\ndan perlu diberikan obat anti reaksi\nObat anti reaksi terdiri atas:\na) Prednison (untuk reaksi tipe 1 dan 2)\nObat ini digunakan untuk penanganan/pengobatan\nreaksi. Cara pemberiannya, dapat dilihat pada\npengobatan reaksi berat.\nb) Klofazimin/Lamprene™ (untuk reaksi tipe 2)\nObat ini dipergunakan untuk penanganan/pengobatan\nreaksi ENL yang berulang (steroid dependent). Cara\npemberiannya, dapat dilihat pada tabel pengobatan\nreaksi berat.\nc) Thalidomid (untuk reaksi tipe 2)\nObat ini tidak dipergunakan dalam program.\n1) Tatalaksana reaksi ringan\nPrinsip pengobatan reaksi ringan\na) Berobat jalan, istirahat di rumah\nb) Pemberian analgetik/antipiretik, obat penenang bila\nperlu\nc) MDT diberikan terus dengan dosis tetap\n- 45 -\nd) Menghindari/menghilangkan faktor pencetus\n2) Tatalaksana reaksi berat\nPrinsip pengobatan reaksi berat antara lain imobilisasi\nlokal/istirahat di rumah. Bila terjadi komplikasi dapat\ndirujuk ke disiplin ilmu terkait (yang tersering: Penyakit\ndalam, saraf, mata, ortopedi). Tatalaksana yang dapat\ndiberikan ialah:\na) MDT tetap diberikan dengan dosis tidak diubah\nb) Menghindari/menghilangkan faktor pencetus\nc) Memberikan obat anti reaksi (Prednison, Klofazimin)\nd) Pemberian analgetik/antipiretik, obat penenang bila\nperlu\ne) Bila ada indikasi rawat inap pasien dikirim ke rumah\nsakit.\nf) Reaksi tipe 2 berat yang berulang diberikan prednison\ndan klofazimin.\nTabel 14. Terapi reaksi berat\nTipe reaksi dan\nPrednison Klofazimin\nneuritis\nSesuai skema. Setiap 2 minggu\nTipe 1 dan 2 berat pasien\nharus diperiksa ulang untuk\nDewasa melihat\nkeadaan klinis dan memeriksa\nfungsi saraf\nBila kondisi:\n• bila membaik, dosis\nprednison\nditurunkan sesuai skema\n• bila menetap, dosis\nprednison\ndilanjutkan selama 1 minggu\n• bila memburuk, dosis\nprednison\ndinaikkan 1 tingkat diatasnya\n- 46 -\nTipe 1 dan Dosis maksimal awal 1 mg/kg BB\nEvaluasi tiap 2 minggu, untuk\n2 berat anak penurunan\nDosis\nTotal lama pengobatan maksimal\n12 minggu\nNeuritis Pada neuritis yang terjadi < dari 6\nbulan diberikan prednison dengan\ndosis standar 12 minggu.\nDosis dimulai 40-60 mg/hari\ndengan dosis maksimal 1mg/kg\nberat badan. Biasanya terjadi\npenyembuhan\ndalam dalam\nbeberapa hari.\nDosis klofazimin\nENL berat Sesuai skema dewasa:\n300 mg/hari\nBerulang selama 2 bulan\n200 mg/hari\n(dependent selama 2 bulan\n100 mg/hari\nsteroid) selama 2 bulan\nCatatan untuk pemberian prednison:\n1) Pemberian prednison harus di bawah pengawasan dokter\npuskesmas/petugas kabupaten dan harus dicatat pada formulir\nevaluasi pengobatan reaksi berat.\n2) Kondisi pasien yang mungkin merupakan kontra indikasi\npemberian prednison: TB, kencing manis, tukak lambung berat,\ninfeksi sekunder pada luka di tangan atau kaki yang memburuk.\nJika kondisi tersebut berat, maka pengobatan reaksi harus di unit\nrujukan (rumah sakit rujukan)\n3) Untuk reaksi, prednison diberikan dalam dosis tunggal pagi hari\nsesudah makan, kecuali jika keadaan terpaksa dapat diberikan\nsecara dosis bagi, misalnya 2 x 4 tablet/hari.\n- 47 -\n4) Perlu diingat bahwa prednison bisa menyebabkan efek samping\nyang serius. Oleh karena itu pasien harus mematuhi aturan\npemberian prednison. Tidak boleh dihentikan tiba-tiba karena\ndapat menyebabkan rebound phenomena (demam, nyeri otot,\nnyeri sendi, malaise). Sementara efek samping pemakaian jangka\npanjang adalah: gangguan cairan dan elektrolit, hiperglikemi,\nmudah infeksi, perdarahan atau perforasi pada pasien tukak\nlambung, osteoporosis, Cushing Syndrome: moon face, obesitas\nsentral, jerawat, pertumbuhan rambut berlebihan, timbunan\nlemak supraklavikuler.\nSKEMA PEMBERIAN PREDNISON\nMinggu pertama 40mg/hari (1x6 tab) pagi hari sesudah\nmakan\nMinggu kedua 30mg/hari (1x6 tab) pagi hari sesudah\nmakan\nMinggu ketiga 20mg/hari (1x4 tab) pagi hari sesudah\nmakan\nMinggu keempat 15mg/hari (1x3 tab) pagi hari\nsesudah makan\nMinggu kelima 10mg/hari (1x2 tab) pagi hari sesudah\nmakan\nMinggu kedua 5mg/hari (1x1 tab) pagi hari sesudah\nmakan\nCatatan untuk pemberian klofazimin lepas:\n1) Klofazimin lepas diberikan pada penderita ENL berat, berulang\n(setelah terjadi ≥ 2 episode), yang menyebabkan ketergantungan\nterhadap steroid (steroid dependent).\n2) Klofazimin diberikan dalam dosis tunggal, pagi hari sesudah\nmakan, kecuali jika keadaan terpaksa dapat diberikan secara\ndosis terbagi, misalnya 3 x 1 tablet/hari atau 2 x 1 tablet/hari\n- 48 -\nSKEMA PEMBERIAN KLOFAZIMIN\n300 mg/hr atau 3x100 mg selama 2 bulan\n200 mg/hr atau 2x100 mg selama 2 bulan\n100 mg/hr selama 2 bulan\nd. Tata Laksana nyeri neuropatik pada kusta\nPasien dengan kusta, baik yang belum atau sudah menerima\nterapi, dapat mengalami keluhan neuropati yang dapat disertai\nnyeri. Nyeri pada kusta dapat berupa (1) nyeri nosiseptif akibat\nstimulus nosiseptif dan peradangan, ataupun (2) nyeri neuropatik\nakibat keterlibatan dan disfungsi pada jaras somatosensorik\nterutama pada saraf perifer. Nyeri nosiseptif umumnya\nmerupakan bagian dari reaksi kusta dan telah dibahas pada\nbagian sebelumnya, sedangkan nyeri neuropatik dapat terjadi\nsejak awal diagnosis, hingga pasien selesai menerima terapi\nkusta. Hal ini penting untuk diketahui karena memiliki perbedaan\npatofisiologi dan pendekatan tata laksana yang akan\nmempengaruhi keberhasilan terapi dan kualitas hidup pasien.\nNyeri neuropatik memiliki karakteristik berupa nyeri spontan\natau nyeri yang diinduksi oleh stimulasi pada daerah yang\ndiinervasi oleh saraf yang mengalami kerusakan, biasanya\ndisertai dengan munculnya sensasi abnormal pada daerah\ntersebut. Nyeri neuropatik pada kusta ditemukan pada 22-56%\npasien kusta, bahkan lebih tinggi (mencapai 85%) pada pasien\nkusta yang telah menerima terapi. Nyeri ini dapat muncul secara\nakut, atau kronik. Karakteristik nyeri neuropatik diakibatkan\noleh dominasi kerusakan pada serabut saraf berukuran kecil\n(small-fiber sensory neuropathy) dengan karakteristik nyeri yang\ntimbul spontan berupa rasa tersengat listrik, rasa panas/bakar,\nsensasi seperti ditusuk-tusuk (pricking pain), dan juga rasa baal.\nNyeri juga dapat timbul setelah pemberian stimulus seperti\nalodinia atau hiperalgesia. Derajat nyeri yang dikeluhkan pasien\nbervariasi namun yang terbanyak ialah derajat berat (55,5%).\nTata laksana nyeri neuropatik pada kusta meliputi pengobatan\nyang adekuat terhadap kusta yang mendasari ditambah dengan\n- 49 -\ntata laksana sesuai dengan panduan nyeri neuropatik, tercantum\npada gambar 1.\nTerapi Lini Pertama\n Ligan kanal kalsium\nPregabalin, gabapentin\n Inhibitor ambilan serotonin dan noradrenalin\nDuloksetin, venlafaksin\n Antidepresan trisiklik\nTerapi Lini Kedua\n Opioid sintetik\nTramadol\nTerapi Lini Ketiga\n Opioid kuat\nFentanil, morfin, oksikodon, buprenorfin\nGambar 1. Pilihan Tata Laksana NyerI Neuropatik pada Kusta\ne. Tata Laksana Psikiatri\nPengobatan gangguan kejiwaan pada pasien kusta pada intinya\nsama dengan pasien lainnya. Tatalaksana farmakoterapi dan\nnonfarmakoterapi yang dianjurkan, tergantung pada kondisi yang\ndialami. Obat yang dapat diberikan adalah dari golongan anti\ndepresan, antiansietas, hingga antipsikotik, dengan observasi\nketat dari psikiater. Psikoterapi adalah tatalaksana nonfarmologi\nyang akan diberikan pada pasien dengan komorbiditas kusta dan\ngangguan psikiatri. Psikoterapi secara rutin akan membantu\npasien, salah satunya dengan memerbaiki fungsi koping.\nDalam tatalaksana kusta perlu dipertimbangkan penyelesaian\nmasalah psikologis pasien, yang seringkali tidak dikeluhkan.\nKondisi depresi terjadi akibat adanya stigma, sehingga\nmenimbulkan penurunan kualitas hidup, bahkan pengobatan\nmenjadi tidak tuntas.\nUpaya yang dilakukan yaitu merujuk pasien, termasuk\nkeluarganya, pada dokter ahli jiwa (psikiater) untuk konseling dan\npsikoterapi.\n- 50 -\nf. Tata Laksana Bedah\nProsedur pembedahan bisa dilakukan bila pasien sudah\nmendapatkan terapi medikamentosa yang adekuat namun belum\nmenunjukkan perbaikan gejala.\nTatalaksana Operatif dan Rekonstruksi yang dilakukan ialah:\n1) Debridement\nDebridement adalah prosedur membersihkan saraf dari pus,\ndebris, dan jaringan nekrotik.\n2) Neurolisis\nNeurolisis diusahakan sampai betul-betul membebaskan\nsaraf dari jepitan sehingga vaskularisasi pada saraf tersebut\ndapat kembali normal.\na) Eksternal neurolisis\nEksternal neurolisis adalah pembebasan jepitan saraf\ndari jepitan yang berasal dari luar epinerium (tulang,\nfascia, tumor dll).\nb) Ekstraneural neurolisis.\nEkstraneural neurolisis adalah pembebasan jepitan\nsaraf dengan melakukan insisi longitudinal epineurium.\nc) Interfasikular neurolisis.\nInterfasikular neurolisis adalah prosedur melakukan\npembebasan pada derajat fasikulus, jadi melakukan\ninsisi longitudinal pada perineurium, dengan\nmemperhatikan anastomose dari vaskularisasi saraf.\n3) Eksisi lesi granulomatosa\nEksisi lesi granulomatosa adalah tindakan yang cukup\nekstensif dan memerlukan graft yang sesuai dengan besar\ndan panjangnya saraf.\n4) Transposition\nAdalah prosedur memindahkan jalur saraf ke tempat yang\nlebih aman dari kemungkinan jepitan, seperti anteriorisasi n.\nUlnaris.\n5) Rekonstruksi komplikasi paralisis nervus ulnaris.\n- 51 -\n2. Non Farmakologis\na. Tatalaksana Kedokteran Fisik dan Rehabilitasi\nSebelum dilakukan tatalaksana Kedokteran Fisik dan\nRehabilitasi, selalu di awali dengan penilaian keterbatasan\nfungsional dan disabilitas pada pasien kusta yang dilakukan\nmelalui asesmen oleh dokter SpKFR (Spesialis Kedokteran Fisik\ndan Rehabilitasi) secara komprehensif dengan menegakkan\ndiagnosis fungsional berdasarkan ICF (International Classification\nof Functioning, Disability and Health). Selain itu diperlukan\npemeriksaan penunjang yang seperti USG muskuloskeletal,\nlaboratorium, EMG, dan permintaan radiologi.\nKeterbatasan fungsional yang dialami pasien kusta antara lain\ngangguan nyeri, gangguan fungsi tangan, gangguan mobilisasi,\ngangguan ambulasi berjalan, gangguan aktivitas kehidupan\nsehari-hari, dan gangguan partisipasi.\nTujuan tatalaksana Kedokteran Fisik dan Rehabilitasi ialah agar\npenderita kusta dapat kembali ke masyarakat sebagai manusia\nyang produktif dan berguna, melalui layanan rehabilitasi medik\nberupa terapi fisik, terapi okupasi, pemberian ortosis dan\nprosthesis, perawatan luka, supporting psikologis melalui\nperesepan latihan yang sesuai.\nTatalaksana Kedokteran Fisik dan Rehabilitasi sebagai berikut:\n1. Konseling dan Edukasi\na) Konseling\nMembantu pasien agar menyadari potensi yang dimiliki\ndan memanfaatkan potensi mentalnya seoptimal\nmungkin untuk meningkatkan kualitas penyesuaian\nbaik dengan dirinya sendiri maupun lingkungannya.\nKonseling juga diberikan dengan tujuan untuk\nmengurangi tingkat antisosial pasien kusta dengan\ndisabilitas.\nb) Edukasi Kesehatan\nMemberikan informasi kesehatan kepada pasien\nmengenai penyakit kusta: penyebab, pengobatan,\nhendaya, dan disabilitas yang terjadi serta pencegahan\ndisabilitas. Memberikan informasi mengenai\n- 52 -\npenggunaan alat pelindung diri dalam melakukan\naktivitas pekerjaan di rumah maupun di tempat kerja.\nc) Penggunaan Modalitas fisik\nModalitas fisik digunakan untuk mengatasi disabilitas\npasien. Pemberian terapi modalitas fisik pada penderita\nkusta harus sesuai dengan indikasi dan kontraindikasi.\nJenis terapi modalitas fisik yang dapat diberikan adalah\nsebagai berikut: Electrical Stimulation (ES), untuk\nredukasi otot; Laser therapy, untuk membantu proses\npenyembuhan luka dan mengurangi nyeri;\nTranscutaneus Electro Nerve Stimulation (TENS), untuk\nmengurangi nyeri dan desensitisasi sensorik;\nUltrasound Diathermy, untuk meningkatkan\nekstensibilitas jaringan, sehingga dapat meningkatkan\nlingkup gerak sendi; dan terapi panas dan terapi dingin.\nd) Pemberian Terapi Latihan\nTerapi latihan merupakan strategi yang paling penting\ndan mendasar dalam tatalaksana rehabilitasi medik.\nTerapi latihan dapat dicapai dengan latihan setiap hari,\ndengan perhatian khusus yaitu cegah latihan atau\nberhenti latihan jika terdapat luka atau lesi pecah-\npecah pada tangan dan kaki. Kulit harus kuat untuk\nmeregang selama latihan.\nTerapi Latihan terhadap pasien dapat berupa latihan\nlingkup gerak sendi, latihan peregangan, latihan\npenguatan dan massage baik menggunakan alat\nataupun tanpa alat. Latihan dapat dilakukan secara\npasif maupun aktif.\n(1) Latihan Aktif: Pasien menggunakan ototnya yang\nlemah untuk latihan. Hal ini mencegah kontraktur\ndan menguatkan otot yang lemah.\n(2) Latihan Pasif: Pasien dibantu untuk\nmenggerakkan bagian yang paralisis secara pasif\nuntuk mencegah terbentuknya kontraktur.\n- 53 -\nGambar 15. Kontraktur pada tangan.\nProgram latihan harus dibuat dengan preskripsi dan\nperencanaan yang tepat untuk meminimalisasi cedera\nsaraf lanjut dan memastikan efek terapi yang dilakukan.\nTerapi latihan ini meliputi :\n(1) latihan untuk mempertahankan Lingkup Gerak\nSendi (LGS)\n(2) latihan untuk meningkatkan kekuatan dan\nketahanan otot\n(3) latihan untuk meningkatkan ketahanan\nkardiorespirasi\n(4) latihan untuk koordinasi\n(5) latihan untuk memulihkan keseimbangan\n(6) latihan ambulasi\n(7) latihan untuk memulihkan fungsi AKS.\nPemberian peresepan terapi latihan harus disesuaikan\ndengan kondisi tertentu pada pasien meliputi\nhemodinamik yang stabil, tidak adanya tanda-tanda\ninfeksi pada area yang akan dilatih, terapi latihan tidak\nmenimbulkan kerusakan jaringan lebih lanjut,\nimobilisasi diperlukan pada area tendon yang telah\ndilakukan rekonstruksi, jika pasien memiliki gangguan\npsikologis yang signifikan atau tidak sadar, terapi\nlatihan aktif tidak memungkinkan untuk dilakukan.\nLatihan peregangan (stretching) yang dilakukan secara\ngentle sangat efektif untuk mencegah terjadinya\nkontraktur pada sendi. Latihan stretching dilakukan 3\nkali sehari dan di luar waktu tersebut pasien tetap\nmelakukan latihan secara mandiri.\nLatihan penguatan dapat berupa latihan beban dan\nlatihan sirkuit. Dalam melakukan latihan ketahanan\n- 54 -\nperlu memperhatikan kondisi fungsi kardiorespirasi.\nLatihan penguatan dan ketahanan otot diberikan tidak\nhanya pada sisi yang sakit, tetapi juga diberikan pada\nsisi yang sehat. Pemberian latihan ini bertujuan untuk\nmempertahankan trofi otot dan persiapan ambulasi.\nPada ekstermitas bawah yang telah mengalami\namputasi diperlukan bandaging yang tepat (seperti\nelastic bandage, stockings, taping) saat latihan ambulasi\nuntuk mendapatkan bentuk/shape pungtum yang baik,\nmaturasi pungtum dan mengurangi nyeri. Latihan\nambulasi dilakukan dengan atau tanpa alat bantu\nberjalan. Alat bantu berjalan yang dapat digunakan\nadalah crutches, walker yang digunakan pada pasien\nkusta dengan amputasi ekstremitas bawah. Pasien\nkusta dengan deformitas pada kaki (contoh : dropfoot)\nperlu menggunakan AFO (Ankle Foot Orthosis), sepatu\nkhusus dan modified insole untuk membantu ambulasi\nberjalan.\nGambar 16. Latihan LGS tangan dan penguatan otot.\nGambar17. Latihan LGS tangan.\n- 55 -\nGambar18. Latihan LGS kaki.\nGambar 19. Latihan Peregangan.\n2. Okupasi\nBentuk kegiatan yang dilatih yaitu aktifitas sehari-hari\nberupa: perawatan diri, berpakaian, berhias, mobilisasi,\ntransfer, mengurus rumah tangga, produktifitas (pekerjaan),\npemanfaatan waktu luang (leisure). Memberikan alat bantu\nberaktivitas (adaptive devices) untuk ke 2 tangan yang\nmengalami disabilitas.\nDengan target terapi antara lain :\na. Perbaikan fungsi fisik, peningkatan lingkup gerak sendi,\nkekuatan otot dan koordinasi. Bentuk kegiatan latihan\ndisesuaian dengan pekerjaan atau hobi dari pasien.\nb. Pasien kusta mampu latih dalam merawat diri sendiri\ndalam kehidupan sehari-hari.\nc. Pasien kusta mampu menggunakan adaptive devices\nsederhana\nd. Meningkatkan toleransi dalam bekerja dan\nmengembangkan kemampuan yang sudah ada\nsebagaimana tujuan dari terapi vokasional pasien.\ne. Mampu mengatur penempatan pekerjaan untuk\nmeminimalisasi kerugian produksi\n- 56 -\nf. Penentuan kemampuan fisik dan mental, status sosial,\nminat, kebiasaan kerja dan kemampuan kerja pasien\nmelalui eksplorasi pre-vokasional\ng. Pemberian terapi diversional yaitu sebagai kegiatan\nuntuk memanfaatkan waktu selama masa perawatan di\nrumah sakit.\nh. Mengukur kemampuan pasien dalam bekerja dan\nmengajarkan pasien agar melindungi daerah tubuh\nyang telah hilang sensasi.\n3. Pemberian Ortosis, Prostesis, Sepatu khusus\na. Pemberian ortosis pada penderita kusta berupa ortosis\nuntuk anggota gerak atas dan bawah dalam melakukan\naktivitas sehari-hari. Seperti splint tangan dan kaki,\nsplint knuckelbender, AFO (ankle foot orthosis) hingga\nalas kaki/sepatu khusus.\nTujuan pemberian splint meliputi :\n1) Memposisikan bagian tubuh atau sendi dengan\ntepat sesuai dengan posisi anatomis (contoh:\nuntuk sendi tangan yang berpotensi mengalami\nkontraktur)\n2) Memberikan topangan, proteksi dan imobilisasi\ntendon atau sendi yang terganggu (contoh: pada\nkaki yang mengalami drop foot)\n3) Membantu mengurangi nyeri dan edema pada\npasien\n4) Memberikan proteksi pada grafts/flap (pasca\nrekonstruksi) yang baru terpasang\n5) Memposisikan sendi yang kontraktur atau bagian\ntubuh yang mengalami deformitas\n6) Menjaga dan meningkatkan posisi dalam\npergerakan.\nDalam pemasangan splint diperlukan monitor dan\nevaluasi untuk melihat kondisi kulit dan penekanan\nsaraf pada sekitar sendi. Sebagai contoh, nervus\nperoneus di bawah caput fibula sering mengalami\n- 57 -\npenekanan akibat pemasangan splint yang tidak tepat\ndan mengakibatkan drop foot permanen. Setelah\npemasangan splint, pasien harus diberikan edukasi\nmengenai bagaimana, kapan dan hingga berapa lama\npasien harus mengenakan splint serta cara\nmembersihkan dan merawat splint.\nGambar 20. Splint statis & dinamis.\nb. Pemberian prostesis pada penderita diperlukan pada\nanggota gerak atas dan bawah apabila telah dilakukan\namputasi dengan tujuan untuk membantu ambulasi.\nJuga prostesis jari-jari dan tangan pada pasien mutilasi,\nuntuk membantu fungsional dan kosmesis sehingga\nmenambah self esteem dan kualitas hidup pasien.\nc. Pemberian alas kaki, sendal hingga sepatu khusus\ndilakukan untuk menghindari terjadinya luka lebih\nlanjut pada pedis, dimana terjadi gangguan sensibilitas\nhingga di perifer. Dibuat secara customize dari bahan\nkhusus, sesuai preskripsi dokter Sp.KFR. Sepatu atau\nsandal khusus juga diberikan jika terjadi drop foot, di\nadjust dengan memakai spring di bagian depan\nsepatu/sendal, sehingga membantu gerakan foot\nclearance pasien saat berjalan.\n4. Perawatan rehabilitasi medik pada pasien kusta yang\nmengalami luka\na. Luka yang timbul pada penderita kusta perlu dilakukan\nperawatan luka dan melindungi luka dengan\nmengurangi tekanan pada area luka, membatasi\n- 58 -\nmobilitas, mengurangi weight baring pada area luka\nterutama ekstremitas bawah berupa penggunaan bidai,\ngips, kursi roda, tongkat, modifikasi sepatu atau alas\nkaki, dan lainnya.\n5. Rehabilitasi Karya/Pelatihan:\na. Pelatihan Vokasional yaitu berupa:\n1) Keterampilan menjahit\n2) Keterampilan las\n3) Keterampilan dalam percetakan\n4) Keterampilan bertani dan berternak\nb. Menyediakan bengkel kerja (workshop)\nc. Penderita kusta dengan disabilitas yang berat perlu\ndiberikan alat bantu modifikasi untuk melakukan\naktivitas sehari-hari maupun pekerjaan lain.\n- 59 -",
    "year": 2019,
    "source_type": "pnpk",
    "score": 0.0,
    "retrieval_method": "hybrid",
    "source_url": "https://kemkes.go.id/app_asset/file_content_download/1701156043656594cb42cf52.71103349.pdf"
  },
  {
    "doc_id": "pnpk-kusta-2019",
    "page": 59,
    "section_slug": "kesimpulan",
    "section_path": "bab_4/kesimpulan",
    "text": "A. Kesimpulan\nBerdasarkan pemeriksaan klinis dan pemeriksaan penunjang, dibuat\ntata alur diagnostik dan klasifikasi kusta untuk memudahkan petugas\nkesehatan di lapangan. Tata alur dapat dilihat pada Gambar 21`.\nGambar 21. Algoritma diagnostik dan klasifikasi kusta.5\nGambar 21. Tata alur diagnostik kasus kusta\nDalam melakukan tata laksana kusta, perlu diketahui komplikasi yang\nmenyertai, karena diperlukan penanganan secara komprehensif bersama\ndisiplin ilmu lain. Bila dijumpai komplikasi maka harus dilakukan rujukan\nsesuai dengan fasilitas kesehatan setempat. Rujukan dilakukan dengan\nmelihat tata alur berikut (Gambar 4.2.), dengan memperhatikan fasilitas\nyang tersedia di Pemberi Pelayanan Kesehatan (PPK).\n- 60 -\nGambar 22. Algoritma rujukan kasus kusta\nPenanganan kasus kusta di layanan kesehatan sesuai dengan Pemberi\nPelayanan Kesehatan (PPK) sebagai berikut:\nPPK I: pemberi pelayanan kesehatan di tingkat I, terdiri dari dokter\npuskesmas, dokter umum praktik swasta/bersama.\n1. PB dan MB tanpa komplikasi\n2. Reaksi reversal dan ENL ringan\nPPK II: pemberi pelayanan kesehatan di tingkat II, terdiri dari dokter\nspesialis praktik perorangan atau bersama.\n1. Kusta tipe PB dan MB dengan komplikasi\n2. Reaksi reversal dan ENL berat\n3. Melibatkan disiplin ilmu terkait (Kulit, Neurologi, Bedah, Mata, Kedokteran\nFisik dan Rehabilitasi, dan lain-lain)\n- 61 -\nPPK III: pemberi pelayanan kesehatan di tingkat III, yaitu pada tahap\nperujukan rumah sakit.\n1. Bila diperlukan tatalaksana khusus dengan sarana lebih lengkap.\nContoh: tindakan bedah vaskular, rekonstruksi flap, dan lain-lain",
    "year": 2019,
    "source_type": "pnpk",
    "score": 0.0,
    "retrieval_method": "hybrid",
    "source_url": "https://kemkes.go.id/app_asset/file_content_download/1701156043656594cb42cf52.71103349.pdf"
  },
  {
    "doc_id": "pnpk-kusta-2019",
    "page": 61,
    "section_slug": "rekomendasi",
    "section_path": "bab_4/rekomendasi",
    "text": "B. Rekomendasi\nRekomendasi Program Tatalaksana Kusta Derajat\nRekomendasi\n1. PERDOSKI A\n2. Program tatalaksana Kedokteran Fisik dan A\nRehabilitasi diberikan sedini mungkin sebagai\npreventif rehabilitasi.\n3. Diperlukan asesmen komprehensif dan uji fungsi, A\ntermasuk pemeriksaan penunjang medik untuk\nmenegakkan diagnosis fungsional berdasarkan ICF\n4. Pasien diberikan pencegahan sindroma dekondisi B\npada saat perawatan reaksi kusta, seperti proper\npositioning untuk mencegah kontraktur sehingga\nmencapai aktivitas fungsional yang optimal sesuai B\ntoleransi.\n5. Penggunaan splint penting diberikan untuk B\nmencapai target posisi sendi yang diharapkan.\n6. Pemberian terapi modalitas fisik sesuai indikasi dan B\nkontraindikasi\n7. Pemberian terapi latihan, okupasi, ortosis &\nprostesis pada setiap pasien kusta sesuai indikasi B\ndan kontraindikasi.\n8. Pemberian perawatan luka dan rehabilitasi karya\nbagi setiap pasien kusta sesuai dengan indikasi.\n- 62 -",
    "year": 2019,
    "source_type": "pnpk",
    "score": 0.0,
    "retrieval_method": "hybrid",
    "source_url": "https://kemkes.go.id/app_asset/file_content_download/1701156043656594cb42cf52.71103349.pdf"
  }
]